{
"meta":{"test_sets":[],"test_metrics":[],"learn_metrics":[{"best_value":"Min","name":"RMSE"}],"launch_mode":"Train","parameters":"","iteration_count":1000,"learn_sets":["learn"],"name":"experiment"},
"iterations":[
{"learn":[14.61268541],"iteration":0,"passed_time":0.1422895267,"remaining_time":142.1472372},
{"learn":[14.23196558],"iteration":1,"passed_time":0.1431864731,"remaining_time":71.45005009},
{"learn":[13.86674177],"iteration":2,"passed_time":0.1440978309,"remaining_time":47.88851248},
{"learn":[13.49946468],"iteration":3,"passed_time":0.1449473321,"remaining_time":36.0918857},
{"learn":[13.16661202],"iteration":4,"passed_time":0.1458421525,"remaining_time":29.02258835},
{"learn":[12.85632158],"iteration":5,"passed_time":0.1466983929,"remaining_time":24.30303376},
{"learn":[12.56784336],"iteration":6,"passed_time":0.1475442738,"remaining_time":20.93020913},
{"learn":[12.31617801],"iteration":7,"passed_time":0.1483580131,"remaining_time":18.39639362},
{"learn":[12.01509946],"iteration":8,"passed_time":0.1492154469,"remaining_time":16.43027865},
{"learn":[11.71512571],"iteration":9,"passed_time":0.1500367076,"remaining_time":14.85363406},
{"learn":[11.43264457],"iteration":10,"passed_time":0.1508727405,"remaining_time":13.56483094},
{"learn":[11.17973129],"iteration":11,"passed_time":0.1517089538,"remaining_time":12.49070386},
{"learn":[10.93746433],"iteration":12,"passed_time":0.1526967692,"remaining_time":11.59320855},
{"learn":[10.69387075],"iteration":13,"passed_time":0.1537990095,"remaining_time":10.83184453},
{"learn":[10.4615922],"iteration":14,"passed_time":0.1547788532,"remaining_time":10.16381136},
{"learn":[10.2299235],"iteration":15,"passed_time":0.1556799705,"remaining_time":9.574318188},
{"learn":[10.01419731],"iteration":16,"passed_time":0.1565867663,"remaining_time":9.054399486},
{"learn":[9.795856918],"iteration":17,"passed_time":0.157549499,"remaining_time":8.595200444},
{"learn":[9.60040151],"iteration":18,"passed_time":0.1584526431,"remaining_time":8.18116015},
{"learn":[9.418664989],"iteration":19,"passed_time":0.1593838885,"remaining_time":7.809810537},
{"learn":[9.249278645],"iteration":20,"passed_time":0.1603172174,"remaining_time":7.473835992},
{"learn":[9.090113396],"iteration":21,"passed_time":0.1613109798,"remaining_time":7.171006282},
{"learn":[8.909548708],"iteration":22,"passed_time":0.162167501,"remaining_time":6.888593411},
{"learn":[8.740140208],"iteration":23,"passed_time":0.1630444504,"remaining_time":6.630474317},
{"learn":[8.59377682],"iteration":24,"passed_time":0.1638999688,"remaining_time":6.392098782},
{"learn":[8.453885414],"iteration":25,"passed_time":0.1647565,"remaining_time":6.172031962},
{"learn":[8.317732234],"iteration":26,"passed_time":0.165579255,"remaining_time":5.966985745},
{"learn":[8.180896085],"iteration":27,"passed_time":0.166426941,"remaining_time":5.777392381},
{"learn":[8.053220863],"iteration":28,"passed_time":0.1673221425,"remaining_time":5.602406909},
{"learn":[7.924234474],"iteration":29,"passed_time":0.1681967653,"remaining_time":5.438362078},
{"learn":[7.818879511],"iteration":30,"passed_time":0.1690580501,"remaining_time":5.284427437},
{"learn":[7.719346395],"iteration":31,"passed_time":0.1698800128,"remaining_time":5.138870387},
{"learn":[7.624163594],"iteration":32,"passed_time":0.1707244596,"remaining_time":5.002744013},
{"learn":[7.524952543],"iteration":33,"passed_time":0.1715386201,"remaining_time":4.873714912},
{"learn":[7.424464745],"iteration":34,"passed_time":0.1723535026,"remaining_time":4.752032287},
{"learn":[7.327482321],"iteration":35,"passed_time":0.1731481776,"remaining_time":4.636523422},
{"learn":[7.238666841],"iteration":36,"passed_time":0.1739795471,"remaining_time":4.528170375},
{"learn":[7.158842395],"iteration":37,"passed_time":0.1747826962,"remaining_time":4.424761941},
{"learn":[7.074348246],"iteration":38,"passed_time":0.1755793067,"remaining_time":4.326454197},
{"learn":[6.992269093],"iteration":39,"passed_time":0.1763862064,"remaining_time":4.233268955},
{"learn":[6.925219745],"iteration":40,"passed_time":0.1771752854,"remaining_time":4.14417314},
{"learn":[6.86013671],"iteration":41,"passed_time":0.1779837397,"remaining_time":4.059724347},
{"learn":[6.786739622],"iteration":42,"passed_time":0.1787601525,"remaining_time":3.978452697},
{"learn":[6.73057926],"iteration":43,"passed_time":0.1795476671,"remaining_time":3.90108113},
{"learn":[6.666356486],"iteration":44,"passed_time":0.1803243006,"remaining_time":3.82688238},
{"learn":[6.606182832],"iteration":45,"passed_time":0.1811850338,"remaining_time":3.757620049},
{"learn":[6.547854615],"iteration":46,"passed_time":0.1819656286,"remaining_time":3.689643491},
{"learn":[6.49240675],"iteration":47,"passed_time":0.1827694597,"remaining_time":3.624927617},
{"learn":[6.431317261],"iteration":48,"passed_time":0.183560053,"remaining_time":3.562563477},
{"learn":[6.377586395],"iteration":49,"passed_time":0.1843264975,"remaining_time":3.502203452},
{"learn":[6.327558015],"iteration":50,"passed_time":0.1851068616,"remaining_time":3.444439445},
{"learn":[6.282040317],"iteration":51,"passed_time":0.1858993102,"remaining_time":3.389087425},
{"learn":[6.237655841],"iteration":52,"passed_time":0.1867159879,"remaining_time":3.33622718},
{"learn":[6.192792003],"iteration":53,"passed_time":0.1874982876,"remaining_time":3.284692223},
{"learn":[6.150579347],"iteration":54,"passed_time":0.188311385,"remaining_time":3.235531979},
{"learn":[6.115693845],"iteration":55,"passed_time":0.1891086473,"remaining_time":3.187831483},
{"learn":[6.078780782],"iteration":56,"passed_time":0.1899051374,"remaining_time":3.14176394},
{"learn":[6.045146957],"iteration":57,"passed_time":0.190704225,"remaining_time":3.097299654},
{"learn":[6.008080327],"iteration":58,"passed_time":0.1914946678,"remaining_time":3.054177669},
{"learn":[5.977575734],"iteration":59,"passed_time":0.1922604705,"remaining_time":3.012080704},
{"learn":[5.948036502],"iteration":60,"passed_time":0.1930399722,"remaining_time":2.971549736},
{"learn":[5.914888282],"iteration":61,"passed_time":0.1938401528,"remaining_time":2.932613925},
{"learn":[5.884957796],"iteration":62,"passed_time":0.1946260628,"remaining_time":2.894676521},
{"learn":[5.849539885],"iteration":63,"passed_time":0.1954540527,"remaining_time":2.858515521},
{"learn":[5.821387627],"iteration":64,"passed_time":0.1962496402,"remaining_time":2.822975594},
{"learn":[5.797012279],"iteration":65,"passed_time":0.1970388295,"remaining_time":2.788397982},
{"learn":[5.768685095],"iteration":66,"passed_time":0.1978023958,"remaining_time":2.754472169},
{"learn":[5.755484587],"iteration":67,"passed_time":0.1982414271,"remaining_time":2.717073678},
{"learn":[5.731887055],"iteration":68,"passed_time":0.1990379373,"remaining_time":2.68556985},
{"learn":[5.707148487],"iteration":69,"passed_time":0.1998319604,"remaining_time":2.654910331},
{"learn":[5.685365039],"iteration":70,"passed_time":0.200645479,"remaining_time":2.625347184},
{"learn":[5.663541834],"iteration":71,"passed_time":0.2014435136,"remaining_time":2.596383064},
{"learn":[5.638108797],"iteration":72,"passed_time":0.2022144107,"remaining_time":2.56784601},
{"learn":[5.619204893],"iteration":73,"passed_time":0.2030016344,"remaining_time":2.540263696},
{"learn":[5.598472793],"iteration":74,"passed_time":0.2037941432,"remaining_time":2.5134611},
{"learn":[5.577007075],"iteration":75,"passed_time":0.2045797924,"remaining_time":2.487259582},
{"learn":[5.562637084],"iteration":76,"passed_time":0.2053557741,"remaining_time":2.461602331},
{"learn":[5.54729991],"iteration":77,"passed_time":0.2061284965,"remaining_time":2.436544535},
{"learn":[5.530737623],"iteration":78,"passed_time":0.2069231213,"remaining_time":2.412356895},
{"learn":[5.513704873],"iteration":79,"passed_time":0.2076826561,"remaining_time":2.388350545},
{"learn":[5.501575529],"iteration":80,"passed_time":0.2084442367,"remaining_time":2.364941401},
{"learn":[5.484080734],"iteration":81,"passed_time":0.2092498829,"remaining_time":2.342577957},
{"learn":[5.472178894],"iteration":82,"passed_time":0.2101198625,"remaining_time":2.321444746},
{"learn":[5.458923342],"iteration":83,"passed_time":0.2109582219,"remaining_time":2.300449182},
{"learn":[5.451382371],"iteration":84,"passed_time":0.2115607191,"remaining_time":2.277388918},
{"learn":[5.441410748],"iteration":85,"passed_time":0.2124306686,"remaining_time":2.257693385},
{"learn":[5.434047468],"iteration":86,"passed_time":0.2129810974,"remaining_time":2.235077494},
{"learn":[5.422107497],"iteration":87,"passed_time":0.2137804657,"remaining_time":2.215543009},
{"learn":[5.40731265],"iteration":88,"passed_time":0.2145994801,"remaining_time":2.196630633},
{"learn":[5.396360181],"iteration":89,"passed_time":0.2153973742,"remaining_time":2.177906783},
{"learn":[5.383793239],"iteration":90,"passed_time":0.2161892511,"remaining_time":2.159516805},
{"learn":[5.369605034],"iteration":91,"passed_time":0.2169708889,"remaining_time":2.141408339},
{"learn":[5.357467333],"iteration":92,"passed_time":0.2177746097,"remaining_time":2.12388786},
{"learn":[5.341109968],"iteration":93,"passed_time":0.2185715912,"remaining_time":2.106658102},
{"learn":[5.330529276],"iteration":94,"passed_time":0.2193828434,"remaining_time":2.089910245},
{"learn":[5.319862075],"iteration":95,"passed_time":0.220179855,"remaining_time":2.073360301},
{"learn":[5.313052243],"iteration":96,"passed_time":0.2211005992,"remaining_time":2.058287022},
{"learn":[5.299677207],"iteration":97,"passed_time":0.2220191372,"remaining_time":2.043482263},
{"learn":[5.287546698],"iteration":98,"passed_time":0.2228555812,"remaining_time":2.028210896},
{"learn":[5.279803754],"iteration":99,"passed_time":0.2240714676,"remaining_time":2.016643208},
{"learn":[5.272254612],"iteration":100,"passed_time":0.2249744111,"remaining_time":2.002495006},
{"learn":[5.268813888],"iteration":101,"passed_time":0.2254224982,"remaining_time":1.984601994},
{"learn":[5.258113767],"iteration":102,"passed_time":0.2262034541,"remaining_time":1.969946585},
{"learn":[5.251018576],"iteration":103,"passed_time":0.2269389604,"remaining_time":1.955166428},
{"learn":[5.24171237],"iteration":104,"passed_time":0.2276704051,"remaining_time":1.940619167},
{"learn":[5.233984943],"iteration":105,"passed_time":0.2284664631,"remaining_time":1.926877528},
{"learn":[5.226240449],"iteration":106,"passed_time":0.2292467971,"remaining_time":1.913246634},
{"learn":[5.220541644],"iteration":107,"passed_time":0.2299724754,"remaining_time":1.899402297},
{"learn":[5.211712096],"iteration":108,"passed_time":0.2307182309,"remaining_time":1.885962787},
{"learn":[5.203388597],"iteration":109,"passed_time":0.2315317997,"remaining_time":1.873302743},
{"learn":[5.196026544],"iteration":110,"passed_time":0.232237471,"remaining_time":1.859991997},
{"learn":[5.188716772],"iteration":111,"passed_time":0.2329705905,"remaining_time":1.847123968},
{"learn":[5.182163132],"iteration":112,"passed_time":0.2336676572,"remaining_time":1.834187717},
{"learn":[5.17764747],"iteration":113,"passed_time":0.2343553974,"remaining_time":1.821393703},
{"learn":[5.170548056],"iteration":114,"passed_time":0.2350442307,"remaining_time":1.808818645},
{"learn":[5.165901827],"iteration":115,"passed_time":0.2356164416,"remaining_time":1.795559779},
{"learn":[5.160333668],"iteration":116,"passed_time":0.2363139095,"remaining_time":1.783463095},
{"learn":[5.148953243],"iteration":117,"passed_time":0.2372151582,"remaining_time":1.773082792},
{"learn":[5.144729126],"iteration":118,"passed_time":0.2379823849,"remaining_time":1.761869589},
{"learn":[5.139939946],"iteration":119,"passed_time":0.2388526854,"remaining_time":1.751586359},
{"learn":[5.132898872],"iteration":120,"passed_time":0.2396361383,"remaining_time":1.740827815},
{"learn":[5.129073077],"iteration":121,"passed_time":0.2403451391,"remaining_time":1.729696985},
{"learn":[5.127123916],"iteration":122,"passed_time":0.2407452996,"remaining_time":1.716533559},
{"learn":[5.121282057],"iteration":123,"passed_time":0.2415417107,"remaining_time":1.706375311},
{"learn":[5.114489821],"iteration":124,"passed_time":0.2423218941,"remaining_time":1.696253258},
{"learn":[5.107777291],"iteration":125,"passed_time":0.2431273388,"remaining_time":1.686454715},
{"learn":[5.103518754],"iteration":126,"passed_time":0.2438287178,"remaining_time":1.676082446},
{"learn":[5.101133351],"iteration":127,"passed_time":0.2442777476,"remaining_time":1.664142156},
{"learn":[5.096462705],"iteration":128,"passed_time":0.2449646053,"remaining_time":1.653985823},
{"learn":[5.08562082],"iteration":129,"passed_time":0.2456527767,"remaining_time":1.643983967},
{"learn":[5.080483682],"iteration":130,"passed_time":0.2463295556,"remaining_time":1.634048731},
{"learn":[5.07437499],"iteration":131,"passed_time":0.2469953031,"remaining_time":1.624181235},
{"learn":[5.070683732],"iteration":132,"passed_time":0.2476464389,"remaining_time":1.614356861},
{"learn":[5.06432037],"iteration":133,"passed_time":0.2483047151,"remaining_time":1.604715547},
{"learn":[5.057436484],"iteration":134,"passed_time":0.2489640944,"remaining_time":1.595214383},
{"learn":[5.053254656],"iteration":135,"passed_time":0.2496202044,"remaining_time":1.585822475},
{"learn":[5.04801663],"iteration":136,"passed_time":0.2503099002,"remaining_time":1.576769663},
{"learn":[5.045680836],"iteration":137,"passed_time":0.2508570998,"remaining_time":1.566947971},
{"learn":[5.041857933],"iteration":138,"passed_time":0.2516207162,"remaining_time":1.558600264},
{"learn":[5.035264888],"iteration":139,"passed_time":0.2523448601,"remaining_time":1.550118426},
{"learn":[5.028771948],"iteration":140,"passed_time":0.253049338,"remaining_time":1.541626818},
{"learn":[5.024912247],"iteration":141,"passed_time":0.2537589705,"remaining_time":1.533276033},
{"learn":[5.02239068],"iteration":142,"passed_time":0.2544381563,"remaining_time":1.52484965},
{"learn":[5.017110572],"iteration":143,"passed_time":0.25514469,"remaining_time":1.516693435},
{"learn":[5.010707886],"iteration":144,"passed_time":0.2558564286,"remaining_time":1.508670665},
{"learn":[5.004389868],"iteration":145,"passed_time":0.2565224469,"remaining_time":1.500480614},
{"learn":[4.997628683],"iteration":146,"passed_time":0.2572414461,"remaining_time":1.492700364},
{"learn":[4.991497851],"iteration":147,"passed_time":0.2579446504,"remaining_time":1.484924609},
{"learn":[4.988345253],"iteration":148,"passed_time":0.2586560179,"remaining_time":1.477290411},
{"learn":[4.98460423],"iteration":149,"passed_time":0.259363053,"remaining_time":1.469723967},
{"learn":[4.982441783],"iteration":150,"passed_time":0.2600624263,"remaining_time":1.462205298},
{"learn":[4.977461771],"iteration":151,"passed_time":0.2607682681,"remaining_time":1.454812443},
{"learn":[4.973601586],"iteration":152,"passed_time":0.2614598291,"remaining_time":1.447427943},
{"learn":[4.968328804],"iteration":153,"passed_time":0.2621361768,"remaining_time":1.44004679},
{"learn":[4.9640736],"iteration":154,"passed_time":0.2628501417,"remaining_time":1.432957224},
{"learn":[4.960865882],"iteration":155,"passed_time":0.2635498761,"remaining_time":1.425872407},
{"learn":[4.957014156],"iteration":156,"passed_time":0.2642826647,"remaining_time":1.41904641},
{"learn":[4.952244852],"iteration":157,"passed_time":0.2650152627,"remaining_time":1.412296526},
{"learn":[4.949695675],"iteration":158,"passed_time":0.2658589586,"remaining_time":1.406209963},
{"learn":[4.946584698],"iteration":159,"passed_time":0.266640827,"remaining_time":1.399864342},
{"learn":[4.940192834],"iteration":160,"passed_time":0.2673918776,"remaining_time":1.393427238},
{"learn":[4.936727994],"iteration":161,"passed_time":0.2681264814,"remaining_time":1.386975255},
{"learn":[4.932342063],"iteration":162,"passed_time":0.2688930662,"remaining_time":1.380757647},
{"learn":[4.925830838],"iteration":163,"passed_time":0.2696492916,"remaining_time":1.374553706},
{"learn":[4.922571773],"iteration":164,"passed_time":0.2703740372,"remaining_time":1.368256491},
{"learn":[4.918395814],"iteration":165,"passed_time":0.2711052613,"remaining_time":1.362058964},
{"learn":[4.911142452],"iteration":166,"passed_time":0.2718479682,"remaining_time":1.355984177},
{"learn":[4.908276131],"iteration":167,"passed_time":0.2725365307,"remaining_time":1.349704723},
{"learn":[4.904584645],"iteration":168,"passed_time":0.2732146735,"remaining_time":1.343440199},
{"learn":[4.89795517],"iteration":169,"passed_time":0.2738972088,"remaining_time":1.337262843},
{"learn":[4.895556491],"iteration":170,"passed_time":0.2745689935,"remaining_time":1.331097635},
{"learn":[4.890591233],"iteration":171,"passed_time":0.2752624299,"remaining_time":1.325100535},
{"learn":[4.884629277],"iteration":172,"passed_time":0.275995419,"remaining_time":1.319353824},
{"learn":[4.880550786],"iteration":173,"passed_time":0.2766831993,"remaining_time":1.31345013},
{"learn":[4.876384842],"iteration":174,"passed_time":0.2773961814,"remaining_time":1.307724855},
{"learn":[4.872638238],"iteration":175,"passed_time":0.2783946171,"remaining_time":1.30339298},
{"learn":[4.869137118],"iteration":176,"passed_time":0.279189382,"remaining_time":1.298151759},
{"learn":[4.863587157],"iteration":177,"passed_time":0.2799380659,"remaining_time":1.292747697},
{"learn":[4.858028614],"iteration":178,"passed_time":0.280655611,"remaining_time":1.28725283},
{"learn":[4.853838176],"iteration":179,"passed_time":0.2815377856,"remaining_time":1.282561023},
{"learn":[4.853462329],"iteration":180,"passed_time":0.2819991092,"remaining_time":1.276007019},
{"learn":[4.851573196],"iteration":181,"passed_time":0.2827157417,"remaining_time":1.270667454},
{"learn":[4.848442087],"iteration":182,"passed_time":0.2834517695,"remaining_time":1.265465004},
{"learn":[4.845547104],"iteration":183,"passed_time":0.2841620238,"remaining_time":1.260196801},
{"learn":[4.839868817],"iteration":184,"passed_time":0.2848754773,"remaining_time":1.254991967},
{"learn":[4.836336958],"iteration":185,"passed_time":0.2855870855,"remaining_time":1.249827353},
{"learn":[4.831124789],"iteration":186,"passed_time":0.286256363,"remaining_time":1.244526327},
{"learn":[4.827407333],"iteration":187,"passed_time":0.2869799152,"remaining_time":1.239508996},
{"learn":[4.824088918],"iteration":188,"passed_time":0.2876848243,"remaining_time":1.234457103},
{"learn":[4.820934539],"iteration":189,"passed_time":0.2884008852,"remaining_time":1.229498511},
{"learn":[4.816975227],"iteration":190,"passed_time":0.2891066066,"remaining_time":1.224540549},
{"learn":[4.812340486],"iteration":191,"passed_time":0.2898318938,"remaining_time":1.21970922},
{"learn":[4.806402747],"iteration":192,"passed_time":0.290529101,"remaining_time":1.214803028},
{"learn":[4.801521788],"iteration":193,"passed_time":0.2912333883,"remaining_time":1.209969644},
{"learn":[4.797601172],"iteration":194,"passed_time":0.2918976816,"remaining_time":1.205013506},
{"learn":[4.792694629],"iteration":195,"passed_time":0.2926044761,"remaining_time":1.200275504},
{"learn":[4.789794613],"iteration":196,"passed_time":0.293443619,"remaining_time":1.196117899},
{"learn":[4.785367055],"iteration":197,"passed_time":0.2942271422,"remaining_time":1.191768525},
{"learn":[4.780376856],"iteration":198,"passed_time":0.2949878604,"remaining_time":1.187363197},
{"learn":[4.776691261],"iteration":199,"passed_time":0.2957459097,"remaining_time":1.182983639},
{"learn":[4.773470753],"iteration":200,"passed_time":0.2966393862,"remaining_time":1.179178456},
{"learn":[4.77207327],"iteration":201,"passed_time":0.2974708761,"remaining_time":1.175157223},
{"learn":[4.767347177],"iteration":202,"passed_time":0.2982664937,"remaining_time":1.171026579},
{"learn":[4.763983068],"iteration":203,"passed_time":0.2990266001,"remaining_time":1.166790067},
{"learn":[4.761588849],"iteration":204,"passed_time":0.2997719445,"remaining_time":1.162530224},
{"learn":[4.758558086],"iteration":205,"passed_time":0.3004868019,"remaining_time":1.158186994},
{"learn":[4.753678804],"iteration":206,"passed_time":0.3011842096,"remaining_time":1.153811972},
{"learn":[4.746510889],"iteration":207,"passed_time":0.301887444,"remaining_time":1.149494498},
{"learn":[4.744840601],"iteration":208,"passed_time":0.3025875694,"remaining_time":1.145199844},
{"learn":[4.741702222],"iteration":209,"passed_time":0.3033320914,"remaining_time":1.141106439},
{"learn":[4.739352853],"iteration":210,"passed_time":0.3040542296,"remaining_time":1.136961077},
{"learn":[4.735539287],"iteration":211,"passed_time":0.3049304169,"remaining_time":1.133420606},
{"learn":[4.730726751],"iteration":212,"passed_time":0.3056777168,"remaining_time":1.129428935},
{"learn":[4.726416092],"iteration":213,"passed_time":0.3064397888,"remaining_time":1.125521841},
{"learn":[4.721293082],"iteration":214,"passed_time":0.3071837191,"remaining_time":1.121577765},
{"learn":[4.718443695],"iteration":215,"passed_time":0.3079198573,"remaining_time":1.117635037},
{"learn":[4.711627962],"iteration":216,"passed_time":0.3086150286,"remaining_time":1.113574043},
{"learn":[4.709790764],"iteration":217,"passed_time":0.3092686515,"remaining_time":1.109394888},
{"learn":[4.706913073],"iteration":218,"passed_time":0.309961426,"remaining_time":1.105387551},
{"learn":[4.703846389],"iteration":219,"passed_time":0.3106835141,"remaining_time":1.101514277},
{"learn":[4.701001135],"iteration":220,"passed_time":0.3114352065,"remaining_time":1.097773873},
{"learn":[4.700380864],"iteration":221,"passed_time":0.3121695696,"remaining_time":1.093999663},
{"learn":[4.695837486],"iteration":222,"passed_time":0.3128633369,"remaining_time":1.090111268},
{"learn":[4.691242996],"iteration":223,"passed_time":0.3135554897,"remaining_time":1.086245803},
{"learn":[4.690284609],"iteration":224,"passed_time":0.3142642598,"remaining_time":1.082465784},
{"learn":[4.68827119],"iteration":225,"passed_time":0.3149545572,"remaining_time":1.078649678},
{"learn":[4.686922425],"iteration":226,"passed_time":0.3156430696,"remaining_time":1.074855034},
{"learn":[4.686085874],"iteration":227,"passed_time":0.3163208012,"remaining_time":1.071051134},
{"learn":[4.683230741],"iteration":228,"passed_time":0.316987371,"remaining_time":1.067236957},
{"learn":[4.6773487],"iteration":229,"passed_time":0.3177029004,"remaining_time":1.063614058},
{"learn":[4.671462906],"iteration":230,"passed_time":0.3183819558,"remaining_time":1.059894909},
{"learn":[4.664799601],"iteration":231,"passed_time":0.3190857317,"remaining_time":1.056283801},
{"learn":[4.660979386],"iteration":232,"passed_time":0.3197940304,"remaining_time":1.052712538},
{"learn":[4.656281279],"iteration":233,"passed_time":0.320491749,"remaining_time":1.04913111},
{"learn":[4.651997094],"iteration":234,"passed_time":0.32143909,"remaining_time":1.046386825},
{"learn":[4.650151977],"iteration":235,"passed_time":0.3222971557,"remaining_time":1.043368758},
{"learn":[4.648478046],"iteration":236,"passed_time":0.3229859187,"remaining_time":1.039823865},
{"learn":[4.646364602],"iteration":237,"passed_time":0.3236706303,"remaining_time":1.036290001},
{"learn":[4.642635873],"iteration":238,"passed_time":0.3243212747,"remaining_time":1.032671507},
{"learn":[4.640860821],"iteration":239,"passed_time":0.3249434981,"remaining_time":1.028987744},
{"learn":[4.639446822],"iteration":240,"passed_time":0.3256006712,"remaining_time":1.025439458},
{"learn":[4.637120072],"iteration":241,"passed_time":0.3262442655,"remaining_time":1.021872534},
{"learn":[4.633769267],"iteration":242,"passed_time":0.3268918512,"remaining_time":1.018342104},
{"learn":[4.630491517],"iteration":243,"passed_time":0.3275585916,"remaining_time":1.014894653},
{"learn":[4.627813333],"iteration":244,"passed_time":0.3282026272,"remaining_time":1.011399933},
{"learn":[4.622496304],"iteration":245,"passed_time":0.3288624477,"remaining_time":1.007976771},
{"learn":[4.618979301],"iteration":246,"passed_time":0.3295224789,"remaining_time":1.004576626},
{"learn":[4.616563458],"iteration":247,"passed_time":0.3301675976,"remaining_time":1.001153361},
{"learn":[4.614759385],"iteration":248,"passed_time":0.3308166776,"remaining_time":0.9977643569},
{"learn":[4.61251363],"iteration":249,"passed_time":0.3314418193,"remaining_time":0.994325458},
{"learn":[4.608796693],"iteration":250,"passed_time":0.3320859452,"remaining_time":0.9909656293},
{"learn":[4.60847774],"iteration":251,"passed_time":0.3327403303,"remaining_time":0.9876578058},
{"learn":[4.605195659],"iteration":252,"passed_time":0.3333778874,"remaining_time":0.9843212724},
{"learn":[4.60103766],"iteration":253,"passed_time":0.3340746232,"remaining_time":0.9811797989},
{"learn":[4.599325598],"iteration":254,"passed_time":0.3349703261,"remaining_time":0.9786387959},
{"learn":[4.597012808],"iteration":255,"passed_time":0.3357098539,"remaining_time":0.9756567629},
{"learn":[4.594161533],"iteration":256,"passed_time":0.3365687719,"remaining_time":0.9730373445},
{"learn":[4.592197259],"iteration":257,"passed_time":0.3372366856,"remaining_time":0.9698822508},
{"learn":[4.58952828],"iteration":258,"passed_time":0.3378970176,"remaining_time":0.9667246721},
{"learn":[4.585816572],"iteration":259,"passed_time":0.3385302524,"remaining_time":0.96350918},
{"learn":[4.582934052],"iteration":260,"passed_time":0.3391425275,"remaining_time":0.9602541297},
{"learn":[4.582234842],"iteration":261,"passed_time":0.3397662151,"remaining_time":0.9570513999},
{"learn":[4.57571562],"iteration":262,"passed_time":0.3404056376,"remaining_time":0.953912376},
{"learn":[4.571197349],"iteration":263,"passed_time":0.3410603937,"remaining_time":0.9508350371},
{"learn":[4.56723703],"iteration":264,"passed_time":0.3417138061,"remaining_time":0.9477722545},
{"learn":[4.560335567],"iteration":265,"passed_time":0.3423876566,"remaining_time":0.9447839848},
{"learn":[4.554709345],"iteration":266,"passed_time":0.3430315619,"remaining_time":0.9417308421},
{"learn":[4.552806306],"iteration":267,"passed_time":0.3436714356,"remaining_time":0.9386846674},
{"learn":[4.550766241],"iteration":268,"passed_time":0.344295745,"remaining_time":0.9356140876},
{"learn":[4.549216045],"iteration":269,"passed_time":0.344927646,"remaining_time":0.932582154},
{"learn":[4.547687452],"iteration":270,"passed_time":0.3455856614,"remaining_time":0.9296381815},
{"learn":[4.545642435],"iteration":271,"passed_time":0.3462174622,"remaining_time":0.9266408546},
{"learn":[4.543930359],"iteration":272,"passed_time":0.3468543273,"remaining_time":0.9236743442},
{"learn":[4.541029943],"iteration":273,"passed_time":0.3475133155,"remaining_time":0.9207834565},
{"learn":[4.537781449],"iteration":274,"passed_time":0.348164311,"remaining_time":0.9178877289},
{"learn":[4.53066128],"iteration":275,"passed_time":0.3489045508,"remaining_time":0.9152423723},
{"learn":[4.526763956],"iteration":276,"passed_time":0.3495671192,"remaining_time":0.9124080403},
{"learn":[4.522036004],"iteration":277,"passed_time":0.3502287951,"remaining_time":0.9095870145},
{"learn":[4.515307629],"iteration":278,"passed_time":0.350909435,"remaining_time":0.9068304754},
{"learn":[4.51109143],"iteration":279,"passed_time":0.3515734074,"remaining_time":0.9040459048},
{"learn":[4.508233494],"iteration":280,"passed_time":0.3522489829,"remaining_time":0.9013061164},
{"learn":[4.502555629],"iteration":281,"passed_time":0.3529014726,"remaining_time":0.8985221891},
{"learn":[4.500081355],"iteration":282,"passed_time":0.3535536414,"remaining_time":0.8957525119},
{"learn":[4.495281743],"iteration":283,"passed_time":0.3542263286,"remaining_time":0.8930494764},
{"learn":[4.492138869],"iteration":284,"passed_time":0.3548767324,"remaining_time":0.8903047848},
{"learn":[4.491708261],"iteration":285,"passed_time":0.3554757798,"remaining_time":0.8874465271},
{"learn":[4.489398865],"iteration":286,"passed_time":0.3561197953,"remaining_time":0.8847157284},
{"learn":[4.485796373],"iteration":287,"passed_time":0.356780719,"remaining_time":0.8820412221},
{"learn":[4.479542205],"iteration":288,"passed_time":0.357492257,"remaining_time":0.8795051721},
{"learn":[4.475986993],"iteration":289,"passed_time":0.358144847,"remaining_time":0.8768373841},
{"learn":[4.468661855],"iteration":290,"passed_time":0.3588045573,"remaining_time":0.8742007942},
{"learn":[4.463785664],"iteration":291,"passed_time":0.3594708463,"remaining_time":0.8715936958},
{"learn":[4.460445831],"iteration":292,"passed_time":0.3601055152,"remaining_time":0.8689235469},
{"learn":[4.45692492],"iteration":293,"passed_time":0.3607368446,"remaining_time":0.8662592255},
{"learn":[4.454031688],"iteration":294,"passed_time":0.361383959,"remaining_time":0.8636464104},
{"learn":[4.451672391],"iteration":295,"passed_time":0.3619980592,"remaining_time":0.8609683571},
{"learn":[4.45031553],"iteration":296,"passed_time":0.3626272024,"remaining_time":0.8583398091},
{"learn":[4.446782666],"iteration":297,"passed_time":0.3635311087,"remaining_time":0.8563719406},
{"learn":[4.444369689],"iteration":298,"passed_time":0.3641850124,"remaining_time":0.8538250625},
{"learn":[4.44411683],"iteration":299,"passed_time":0.3647824953,"remaining_time":0.8511591557},
{"learn":[4.440876943],"iteration":300,"passed_time":0.3653933965,"remaining_time":0.8485381533},
{"learn":[4.439336453],"iteration":301,"passed_time":0.3660018306,"remaining_time":0.8459247608},
{"learn":[4.436666901],"iteration":302,"passed_time":0.3666282861,"remaining_time":0.8433660575},
{"learn":[4.433043336],"iteration":303,"passed_time":0.3672354667,"remaining_time":0.8407759368},
{"learn":[4.431419305],"iteration":304,"passed_time":0.3678365298,"remaining_time":0.8381848793},
{"learn":[4.428859646],"iteration":305,"passed_time":0.3684606887,"remaining_time":0.8356592091},
{"learn":[4.424552441],"iteration":306,"passed_time":0.3690757217,"remaining_time":0.8331253261},
{"learn":[4.422706391],"iteration":307,"passed_time":0.369673355,"remaining_time":0.8305648106},
{"learn":[4.421427994],"iteration":308,"passed_time":0.370270878,"remaining_time":0.8280167531},
{"learn":[4.418733158],"iteration":309,"passed_time":0.370887335,"remaining_time":0.8255234231},
{"learn":[4.415656941],"iteration":310,"passed_time":0.3715068708,"remaining_time":0.8230489839},
{"learn":[4.410747417],"iteration":311,"passed_time":0.3721459222,"remaining_time":0.8206294695},
{"learn":[4.408126521],"iteration":312,"passed_time":0.3727638333,"remaining_time":0.8181749313},
{"learn":[4.407843853],"iteration":313,"passed_time":0.3733417304,"remaining_time":0.8156446722},
{"learn":[4.405219398],"iteration":314,"passed_time":0.374016273,"remaining_time":0.8133369746},
{"learn":[4.402708465],"iteration":315,"passed_time":0.3746324692,"remaining_time":0.8109133195},
{"learn":[4.40104971],"iteration":316,"passed_time":0.3752460681,"remaining_time":0.8084954716},
{"learn":[4.400830038],"iteration":317,"passed_time":0.3758404421,"remaining_time":0.8060477407},
{"learn":[4.39784288],"iteration":318,"passed_time":0.3764563375,"remaining_time":0.8036575732},
{"learn":[4.393741845],"iteration":319,"passed_time":0.3771168701,"remaining_time":0.8013733491},
{"learn":[4.393425936],"iteration":320,"passed_time":0.3778000573,"remaining_time":0.7991471618},
{"learn":[4.390505974],"iteration":321,"passed_time":0.3785457226,"remaining_time":0.7970621116},
{"learn":[4.390305136],"iteration":322,"passed_time":0.3792317679,"remaining_time":0.7948603928},
{"learn":[4.38568203],"iteration":323,"passed_time":0.3799063706,"remaining_time":0.792644156},
{"learn":[4.383057135],"iteration":324,"passed_time":0.3805441083,"remaining_time":0.7903608403},
{"learn":[4.380662684],"iteration":325,"passed_time":0.3811987241,"remaining_time":0.7881225154},
{"learn":[4.37805727],"iteration":326,"passed_time":0.381829211,"remaining_time":0.7858442172},
{"learn":[4.373708319],"iteration":327,"passed_time":0.3824906061,"remaining_time":0.7836392906},
{"learn":[4.36887921],"iteration":328,"passed_time":0.3831384125,"remaining_time":0.7814160327},
{"learn":[4.367895929],"iteration":329,"passed_time":0.3837851959,"remaining_time":0.7792002462},
{"learn":[4.362140573],"iteration":330,"passed_time":0.3844678616,"remaining_time":0.7770664634},
{"learn":[4.361931924],"iteration":331,"passed_time":0.385076045,"remaining_time":0.7747915604},
{"learn":[4.359656377],"iteration":332,"passed_time":0.3857180649,"remaining_time":0.7725944422},
{"learn":[4.354281355],"iteration":333,"passed_time":0.3863701534,"remaining_time":0.7704267131},
{"learn":[4.348589447],"iteration":334,"passed_time":0.3870334639,"remaining_time":0.768290309},
{"learn":[4.346355698],"iteration":335,"passed_time":0.3877434766,"remaining_time":0.7662549658},
{"learn":[4.343894047],"iteration":336,"passed_time":0.3884173072,"remaining_time":0.7641563046},
{"learn":[4.341561356],"iteration":337,"passed_time":0.3890920302,"remaining_time":0.7620678225},
{"learn":[4.338869061],"iteration":338,"passed_time":0.3897566044,"remaining_time":0.7599678923},
{"learn":[4.333720063],"iteration":339,"passed_time":0.390423445,"remaining_time":0.7578808049},
{"learn":[4.330892223],"iteration":340,"passed_time":0.3912042914,"remaining_time":0.7560223697},
{"learn":[4.328311474],"iteration":341,"passed_time":0.391904447,"remaining_time":0.7540149886},
{"learn":[4.324580133],"iteration":342,"passed_time":0.392567236,"remaining_time":0.7519436562},
{"learn":[4.323354432],"iteration":343,"passed_time":0.3931976027,"remaining_time":0.7498186842},
{"learn":[4.323159553],"iteration":344,"passed_time":0.3937996285,"remaining_time":0.7476485701},
{"learn":[4.318639682],"iteration":345,"passed_time":0.3944459005,"remaining_time":0.745571153},
{"learn":[4.312712208],"iteration":346,"passed_time":0.3950957326,"remaining_time":0.7435086842},
{"learn":[4.311461062],"iteration":347,"passed_time":0.3957324574,"remaining_time":0.7414297765},
{"learn":[4.311178356],"iteration":348,"passed_time":0.3963501178,"remaining_time":0.7393235722},
{"learn":[4.311102505],"iteration":349,"passed_time":0.3969665949,"remaining_time":0.7372236762},
{"learn":[4.310232308],"iteration":350,"passed_time":0.3975988669,"remaining_time":0.7351614377},
{"learn":[4.305128197],"iteration":351,"passed_time":0.3982419599,"remaining_time":0.7331272443},
{"learn":[4.304595496],"iteration":352,"passed_time":0.3988818837,"remaining_time":0.731095124},
{"learn":[4.3004992],"iteration":353,"passed_time":0.3995349451,"remaining_time":0.7290948432},
{"learn":[4.297581524],"iteration":354,"passed_time":0.4001611599,"remaining_time":0.727053375},
{"learn":[4.297355825],"iteration":355,"passed_time":0.4007648304,"remaining_time":0.7249790752},
{"learn":[4.295758715],"iteration":356,"passed_time":0.4014136898,"remaining_time":0.7229944048},
{"learn":[4.292500657],"iteration":357,"passed_time":0.4020405665,"remaining_time":0.7209777756},
{"learn":[4.290797586],"iteration":358,"passed_time":0.402643525,"remaining_time":0.7189261825},
{"learn":[4.286410608],"iteration":359,"passed_time":0.4032819747,"remaining_time":0.7169457327},
{"learn":[4.280278245],"iteration":360,"passed_time":0.4039690128,"remaining_time":0.7150587235},
{"learn":[4.279941283],"iteration":361,"passed_time":0.4045982262,"remaining_time":0.7130764318},
{"learn":[4.274426275],"iteration":362,"passed_time":0.4052443377,"remaining_time":0.7111312482},
{"learn":[4.273567658],"iteration":363,"passed_time":0.4058595411,"remaining_time":0.7091391982},
{"learn":[4.269488271],"iteration":364,"passed_time":0.4064961054,"remaining_time":0.7071918546},
{"learn":[4.266838205],"iteration":365,"passed_time":0.4071648916,"remaining_time":0.7053074897},
{"learn":[4.263456509],"iteration":366,"passed_time":0.4077911565,"remaining_time":0.7033564089},
{"learn":[4.260360204],"iteration":367,"passed_time":0.408424261,"remaining_time":0.7014242742},
{"learn":[4.255120549],"iteration":368,"passed_time":0.4090533138,"remaining_time":0.6994922521},
{"learn":[4.252582211],"iteration":369,"passed_time":0.4096777536,"remaining_time":0.6975594183},
{"learn":[4.247857931],"iteration":370,"passed_time":0.4103280169,"remaining_time":0.6956774196},
{"learn":[4.245288911],"iteration":371,"passed_time":0.4109454567,"remaining_time":0.6937466313},
{"learn":[4.24048515],"iteration":372,"passed_time":0.4115749208,"remaining_time":0.6918430974},
{"learn":[4.2378365],"iteration":373,"passed_time":0.4122060897,"remaining_time":0.6899492304},
{"learn":[4.236751063],"iteration":374,"passed_time":0.4128339091,"remaining_time":0.6880565152},
{"learn":[4.233240093],"iteration":375,"passed_time":0.4134579176,"remaining_time":0.6861642037},
{"learn":[4.230358421],"iteration":376,"passed_time":0.4141685029,"remaining_time":0.6844216905},
{"learn":[4.225853583],"iteration":377,"passed_time":0.4148322146,"remaining_time":0.6826075065},
{"learn":[4.224702126],"iteration":378,"passed_time":0.4154700626,"remaining_time":0.6807570154},
{"learn":[4.224361982],"iteration":379,"passed_time":0.4160824881,"remaining_time":0.6788714279},
{"learn":[4.223787954],"iteration":380,"passed_time":0.41668314,"remaining_time":0.6769733954},
{"learn":[4.22144054],"iteration":381,"passed_time":0.4173180797,"remaining_time":0.6751376263},
{"learn":[4.217739335],"iteration":382,"passed_time":0.417969035,"remaining_time":0.6733339284},
{"learn":[4.215611665],"iteration":383,"passed_time":0.4186004446,"remaining_time":0.6715048799},
{"learn":[4.210236863],"iteration":384,"passed_time":0.4192448011,"remaining_time":0.6697027343},
{"learn":[4.208454294],"iteration":385,"passed_time":0.4198696721,"remaining_time":0.6678755924},
{"learn":[4.207446501],"iteration":386,"passed_time":0.4204838526,"remaining_time":0.6660377304},
{"learn":[4.204985442],"iteration":387,"passed_time":0.4211411961,"remaining_time":0.6642742578},
{"learn":[4.202796622],"iteration":388,"passed_time":0.42176356,"remaining_time":0.6624615299},
{"learn":[4.199774004],"iteration":389,"passed_time":0.4223818823,"remaining_time":0.6606485851},
{"learn":[4.199458358],"iteration":390,"passed_time":0.4229892133,"remaining_time":0.6588246314},
{"learn":[4.19751254],"iteration":391,"passed_time":0.4236173937,"remaining_time":0.6570392228},
{"learn":[4.195201346],"iteration":392,"passed_time":0.4242435182,"remaining_time":0.6552565282},
{"learn":[4.190593508],"iteration":393,"passed_time":0.4248978331,"remaining_time":0.6535230631},
{"learn":[4.187212054],"iteration":394,"passed_time":0.4255228946,"remaining_time":0.6517502564},
{"learn":[4.184984466],"iteration":395,"passed_time":0.426146843,"remaining_time":0.6499815484},
{"learn":[4.182832144],"iteration":396,"passed_time":0.426778403,"remaining_time":0.6482301688},
{"learn":[4.179752812],"iteration":397,"passed_time":0.4273951007,"remaining_time":0.6464619363},
{"learn":[4.17878934],"iteration":398,"passed_time":0.4280085391,"remaining_time":0.6446945664},
{"learn":[4.174548229],"iteration":399,"passed_time":0.4286534271,"remaining_time":0.6429801407},
{"learn":[4.168872556],"iteration":400,"passed_time":0.4292791606,"remaining_time":0.6412424369},
{"learn":[4.163926494],"iteration":401,"passed_time":0.4299100086,"remaining_time":0.6395178735},
{"learn":[4.159485076],"iteration":402,"passed_time":0.4305465328,"remaining_time":0.6378071466},
{"learn":[4.155926102],"iteration":403,"passed_time":0.4311743321,"remaining_time":0.6360888662},
{"learn":[4.153540115],"iteration":404,"passed_time":0.4318397587,"remaining_time":0.6344312504},
{"learn":[4.150983044],"iteration":405,"passed_time":0.432565818,"remaining_time":0.6328672313},
{"learn":[4.146539132],"iteration":406,"passed_time":0.4333093372,"remaining_time":0.6313327689},
{"learn":[4.144869174],"iteration":407,"passed_time":0.4339919327,"remaining_time":0.6297137847},
{"learn":[4.142825962],"iteration":408,"passed_time":0.4346598564,"remaining_time":0.6280781788},
{"learn":[4.142467378],"iteration":409,"passed_time":0.4352632461,"remaining_time":0.6263544273},
{"learn":[4.141800768],"iteration":410,"passed_time":0.4358649511,"remaining_time":0.6246337133},
{"learn":[4.140107084],"iteration":411,"passed_time":0.4364653022,"remaining_time":0.6229164992},
{"learn":[4.136243196],"iteration":412,"passed_time":0.4370902032,"remaining_time":0.6212395867},
{"learn":[4.133618439],"iteration":413,"passed_time":0.4377108722,"remaining_time":0.619561766},
{"learn":[4.131053025],"iteration":414,"passed_time":0.4383214625,"remaining_time":0.6178748327},
{"learn":[4.128379975],"iteration":415,"passed_time":0.4389610254,"remaining_time":0.6162337471},
{"learn":[4.127068571],"iteration":416,"passed_time":0.4396298717,"remaining_time":0.6146384057},
{"learn":[4.125969877],"iteration":417,"passed_time":0.4402830934,"remaining_time":0.6130257425},
{"learn":[4.123893633],"iteration":418,"passed_time":0.4409497636,"remaining_time":0.611436307},
{"learn":[4.119643722],"iteration":419,"passed_time":0.4416272946,"remaining_time":0.609866264},
{"learn":[4.11465686],"iteration":420,"passed_time":0.4423803108,"remaining_time":0.6084042755},
{"learn":[4.111565986],"iteration":421,"passed_time":0.4431200993,"remaining_time":0.6069275294},
{"learn":[4.106322452],"iteration":422,"passed_time":0.4437782652,"remaining_time":0.6053429291},
{"learn":[4.104222175],"iteration":423,"passed_time":0.4444330515,"remaining_time":0.6037581076},
{"learn":[4.103008002],"iteration":424,"passed_time":0.4451095609,"remaining_time":0.6022070529},
{"learn":[4.099176337],"iteration":425,"passed_time":0.4457970302,"remaining_time":0.6006748717},
{"learn":[4.096525716],"iteration":426,"passed_time":0.4464916701,"remaining_time":0.5991562692},
{"learn":[4.094967724],"iteration":427,"passed_time":0.447268334,"remaining_time":0.597751138},
{"learn":[4.094683584],"iteration":428,"passed_time":0.4480008718,"remaining_time":0.5962902047},
{"learn":[4.091096563],"iteration":429,"passed_time":0.4486748227,"remaining_time":0.5947549975},
{"learn":[4.089178677],"iteration":430,"passed_time":0.4493534369,"remaining_time":0.5932299433},
{"learn":[4.085335077],"iteration":431,"passed_time":0.4500611339,"remaining_time":0.5917470464},
{"learn":[4.084852122],"iteration":432,"passed_time":0.4507116279,"remaining_time":0.5901928245},
{"learn":[4.080322952],"iteration":433,"passed_time":0.451397232,"remaining_time":0.588688556},
{"learn":[4.077449519],"iteration":434,"passed_time":0.4520660783,"remaining_time":0.5871662856},
{"learn":[4.076568374],"iteration":435,"passed_time":0.4527168932,"remaining_time":0.585624605},
{"learn":[4.076071793],"iteration":436,"passed_time":0.4533514919,"remaining_time":0.5840661097},
{"learn":[4.075027644],"iteration":437,"passed_time":0.4540267264,"remaining_time":0.5825639732},
{"learn":[4.07020837],"iteration":438,"passed_time":0.4546987318,"remaining_time":0.5810614773},
{"learn":[4.06833694],"iteration":439,"passed_time":0.4553683503,"remaining_time":0.5795597185},
{"learn":[4.063936568],"iteration":440,"passed_time":0.4560319817,"remaining_time":0.5780541446},
{"learn":[4.061734926],"iteration":441,"passed_time":0.4566646449,"remaining_time":0.5765132847},
{"learn":[4.060815619],"iteration":442,"passed_time":0.4573257592,"remaining_time":0.5750122977},
{"learn":[4.056407489],"iteration":443,"passed_time":0.4579619925,"remaining_time":0.5734839366},
{"learn":[4.05238936],"iteration":444,"passed_time":0.4585969924,"remaining_time":0.5719580467},
{"learn":[4.049685254],"iteration":445,"passed_time":0.4592096486,"remaining_time":0.5704083975},
{"learn":[4.045162016],"iteration":446,"passed_time":0.459843465,"remaining_time":0.5688891189},
{"learn":[4.042955482],"iteration":447,"passed_time":0.4609020218,"remaining_time":0.567897134},
{"learn":[4.041467663],"iteration":448,"passed_time":0.4616580356,"remaining_time":0.5665335804},
{"learn":[4.038920476],"iteration":449,"passed_time":0.462426556,"remaining_time":0.5651880129},
{"learn":[4.036694383],"iteration":450,"passed_time":0.4631188391,"remaining_time":0.563752201},
{"learn":[4.034999007],"iteration":451,"passed_time":0.4637644492,"remaining_time":0.5622630932},
{"learn":[4.031928018],"iteration":452,"passed_time":0.4644036811,"remaining_time":0.5607700078},
{"learn":[4.028718143],"iteration":453,"passed_time":0.4650413886,"remaining_time":0.5592788507},
{"learn":[4.027401978],"iteration":454,"passed_time":0.4656742123,"remaining_time":0.5577855949},
{"learn":[4.025930598],"iteration":455,"passed_time":0.4663667762,"remaining_time":0.5563673821},
{"learn":[4.021074523],"iteration":456,"passed_time":0.4670363747,"remaining_time":0.5549250579},
{"learn":[4.020268486],"iteration":457,"passed_time":0.467676459,"remaining_time":0.5534511807},
{"learn":[4.017986361],"iteration":458,"passed_time":0.4684329451,"remaining_time":0.5521181335},
{"learn":[4.014814804],"iteration":459,"passed_time":0.4691573798,"remaining_time":0.5507499676},
{"learn":[4.009704796],"iteration":460,"passed_time":0.4698940896,"remaining_time":0.5493989464},
{"learn":[4.008440457],"iteration":461,"passed_time":0.4706031405,"remaining_time":0.5480183757},
{"learn":[4.004854849],"iteration":462,"passed_time":0.4713164234,"remaining_time":0.5466456142},
{"learn":[4.000898028],"iteration":463,"passed_time":0.4720708938,"remaining_time":0.5453232739},
{"learn":[3.996617985],"iteration":464,"passed_time":0.4727839762,"remaining_time":0.5439557576},
{"learn":[3.995443319],"iteration":465,"passed_time":0.4734979612,"remaining_time":0.5425920842},
{"learn":[3.990771995],"iteration":466,"passed_time":0.4742081653,"remaining_time":0.5412268782},
{"learn":[3.989249359],"iteration":467,"passed_time":0.4750746249,"remaining_time":0.540042095},
{"learn":[3.986599538],"iteration":468,"passed_time":0.4758245022,"remaining_time":0.5387266751},
{"learn":[3.985628919],"iteration":469,"passed_time":0.4765440831,"remaining_time":0.5373794979},
{"learn":[3.985086112],"iteration":470,"passed_time":0.477242614,"remaining_time":0.5360113435},
{"learn":[3.98466839],"iteration":471,"passed_time":0.4779893122,"remaining_time":0.5346999085},
{"learn":[3.984233894],"iteration":472,"passed_time":0.4786911726,"remaining_time":0.5333409048},
{"learn":[3.981855845],"iteration":473,"passed_time":0.4794056189,"remaining_time":0.5319986404},
{"learn":[3.978684264],"iteration":474,"passed_time":0.4801432212,"remaining_time":0.5306846129},
{"learn":[3.974361269],"iteration":475,"passed_time":0.4808844036,"remaining_time":0.5293769485},
{"learn":[3.972074049],"iteration":476,"passed_time":0.4816594326,"remaining_time":0.5281087699},
{"learn":[3.97191982],"iteration":477,"passed_time":0.4824122181,"remaining_time":0.5268183637},
{"learn":[3.969616848],"iteration":478,"passed_time":0.483163369,"remaining_time":0.5255284244},
{"learn":[3.968533527],"iteration":479,"passed_time":0.4839028467,"remaining_time":0.5242280839},
{"learn":[3.967568753],"iteration":480,"passed_time":0.4846442097,"remaining_time":0.5229321098},
{"learn":[3.966232553],"iteration":481,"passed_time":0.4853710613,"remaining_time":0.5216228418},
{"learn":[3.961522393],"iteration":482,"passed_time":0.4861253612,"remaining_time":0.5203453659},
{"learn":[3.955829553],"iteration":483,"passed_time":0.486824574,"remaining_time":0.5190113227},
{"learn":[3.954248095],"iteration":484,"passed_time":0.4875305161,"remaining_time":0.5176870428},
{"learn":[3.951922606],"iteration":485,"passed_time":0.4882776856,"remaining_time":0.5164089103},
{"learn":[3.94978202],"iteration":486,"passed_time":0.489085849,"remaining_time":0.5151972085},
{"learn":[3.949518999],"iteration":487,"passed_time":0.4898148267,"remaining_time":0.5139040805},
{"learn":[3.945431216],"iteration":488,"passed_time":0.4905318202,"remaining_time":0.5126007365},
{"learn":[3.943249086],"iteration":489,"passed_time":0.4912262896,"remaining_time":0.5112763422},
{"learn":[3.941981548],"iteration":490,"passed_time":0.4919101687,"remaining_time":0.5099435354},
{"learn":[3.936600517],"iteration":491,"passed_time":0.4926157497,"remaining_time":0.5086357741},
{"learn":[3.934476885],"iteration":492,"passed_time":0.4933179311,"remaining_time":0.5073269595},
{"learn":[3.93045798],"iteration":493,"passed_time":0.4940670762,"remaining_time":0.5060687056},
{"learn":[3.925977375],"iteration":494,"passed_time":0.4947599912,"remaining_time":0.5047551425},
{"learn":[3.92457993],"iteration":495,"passed_time":0.4954514118,"remaining_time":0.5034425636},
{"learn":[3.919849146],"iteration":496,"passed_time":0.4961320919,"remaining_time":0.5021216141},
{"learn":[3.919681964],"iteration":497,"passed_time":0.4967880314,"remaining_time":0.5007782967},
{"learn":[3.917633027],"iteration":498,"passed_time":0.4974812572,"remaining_time":0.49947517},
{"learn":[3.916616419],"iteration":499,"passed_time":0.4981774214,"remaining_time":0.4981774214},
{"learn":[3.912896166],"iteration":500,"passed_time":0.498875862,"remaining_time":0.4968843416},
{"learn":[3.912769674],"iteration":501,"passed_time":0.4995021671,"remaining_time":0.4955220701},
{"learn":[3.909373788],"iteration":502,"passed_time":0.5001736609,"remaining_time":0.4942073747},
{"learn":[3.906706036],"iteration":503,"passed_time":0.5008458869,"remaining_time":0.4928959522},
{"learn":[3.903895664],"iteration":504,"passed_time":0.5015030599,"remaining_time":0.4915723063},
{"learn":[3.902982967],"iteration":505,"passed_time":0.5022538097,"remaining_time":0.4903426521},
{"learn":[3.900905528],"iteration":506,"passed_time":0.5030056024,"remaining_time":0.4891159013},
{"learn":[3.897463465],"iteration":507,"passed_time":0.5037047751,"remaining_time":0.4878400578},
{"learn":[3.895918033],"iteration":508,"passed_time":0.5045130902,"remaining_time":0.4866717629},
{"learn":[3.893921936],"iteration":509,"passed_time":0.5052424691,"remaining_time":0.4854290389},
{"learn":[3.890237934],"iteration":510,"passed_time":0.5059365673,"remaining_time":0.4841545625},
{"learn":[3.887311613],"iteration":511,"passed_time":0.5066365524,"remaining_time":0.482887964},
{"learn":[3.884869735],"iteration":512,"passed_time":0.507394623,"remaining_time":0.4816787162},
{"learn":[3.882101231],"iteration":513,"passed_time":0.508087548,"remaining_time":0.4804096271},
{"learn":[3.88060368],"iteration":514,"passed_time":0.5088103681,"remaining_time":0.4791709292},
{"learn":[3.877726076],"iteration":515,"passed_time":0.5094844995,"remaining_time":0.4778885615},
{"learn":[3.874938145],"iteration":516,"passed_time":0.5101712167,"remaining_time":0.476620305},
{"learn":[3.874340833],"iteration":517,"passed_time":0.5108564698,"remaining_time":0.4753529314},
{"learn":[3.873105224],"iteration":518,"passed_time":0.5115418934,"remaining_time":0.474087959},
{"learn":[3.869800236],"iteration":519,"passed_time":0.5122572823,"remaining_time":0.472852876},
{"learn":[3.867932518],"iteration":520,"passed_time":0.5129171832,"remaining_time":0.471568773},
{"learn":[3.866666962],"iteration":521,"passed_time":0.5136024763,"remaining_time":0.4703103136},
{"learn":[3.865527652],"iteration":522,"passed_time":0.5142922824,"remaining_time":0.469058162},
{"learn":[3.861900081],"iteration":523,"passed_time":0.5150004608,"remaining_time":0.4678248461},
{"learn":[3.858502887],"iteration":524,"passed_time":0.5157018499,"remaining_time":0.466587388},
{"learn":[3.858335097],"iteration":525,"passed_time":0.5163681188,"remaining_time":0.46532032},
{"learn":[3.855719306],"iteration":526,"passed_time":0.5171073558,"remaining_time":0.4641210233},
{"learn":[3.855137428],"iteration":527,"passed_time":0.5177935215,"remaining_time":0.4628760268},
{"learn":[3.851985706],"iteration":528,"passed_time":0.5184903275,"remaining_time":0.4616426167},
{"learn":[3.851051809],"iteration":529,"passed_time":0.5191623929,"remaining_time":0.4603892919},
{"learn":[3.850679146],"iteration":530,"passed_time":0.5198227451,"remaining_time":0.4591278106},
{"learn":[3.848179484],"iteration":531,"passed_time":0.5204974781,"remaining_time":0.4578812402},
{"learn":[3.844551071],"iteration":532,"passed_time":0.5212118643,"remaining_time":0.4566715584},
{"learn":[3.841604794],"iteration":533,"passed_time":0.5219079883,"remaining_time":0.455447795},
{"learn":[3.83969656],"iteration":534,"passed_time":0.5225900924,"remaining_time":0.4542138186},
{"learn":[3.836811463],"iteration":535,"passed_time":0.5232787652,"remaining_time":0.4529875878},
{"learn":[3.834182551],"iteration":536,"passed_time":0.523948835,"remaining_time":0.4517473196},
{"learn":[3.828012842],"iteration":537,"passed_time":0.5246670119,"remaining_time":0.4505504824},
{"learn":[3.826636176],"iteration":538,"passed_time":0.5253579011,"remaining_time":0.4493320824},
{"learn":[3.826189798],"iteration":539,"passed_time":0.5260266271,"remaining_time":0.4480967564},
{"learn":[3.824104738],"iteration":540,"passed_time":0.526699916,"remaining_time":0.4468673964},
{"learn":[3.82300218],"iteration":541,"passed_time":0.5273918481,"remaining_time":0.4456558422},
{"learn":[3.817146402],"iteration":542,"passed_time":0.5280849135,"remaining_time":0.4444471555},
{"learn":[3.814638044],"iteration":543,"passed_time":0.5287728041,"remaining_time":0.4432360269},
{"learn":[3.812979573],"iteration":544,"passed_time":0.5294882131,"remaining_time":0.4420497926},
{"learn":[3.811938825],"iteration":545,"passed_time":0.5301623144,"remaining_time":0.4408309354},
{"learn":[3.811479418],"iteration":546,"passed_time":0.5309325697,"remaining_time":0.4396937003},
{"learn":[3.80742981],"iteration":547,"passed_time":0.5317088723,"remaining_time":0.4385627925},
{"learn":[3.805097043],"iteration":548,"passed_time":0.5324633126,"remaining_time":0.4374152167},
{"learn":[3.801577232],"iteration":549,"passed_time":0.53321675,"remaining_time":0.43626825},
{"learn":[3.799762083],"iteration":550,"passed_time":0.5339018125,"remaining_time":0.4350669942},
{"learn":[3.796393455],"iteration":551,"passed_time":0.5346075339,"remaining_time":0.4338843754},
{"learn":[3.793486459],"iteration":552,"passed_time":0.5352785464,"remaining_time":0.4326754254},
{"learn":[3.792006091],"iteration":553,"passed_time":0.5359561677,"remaining_time":0.4314737379},
{"learn":[3.78932128],"iteration":554,"passed_time":0.5366121374,"remaining_time":0.4302565786},
{"learn":[3.787581812],"iteration":555,"passed_time":0.5372830897,"remaining_time":0.4290534025},
{"learn":[3.785308865],"iteration":556,"passed_time":0.5379468314,"remaining_time":0.4278464027},
{"learn":[3.78465475],"iteration":557,"passed_time":0.5385765863,"remaining_time":0.4266144286},
{"learn":[3.780498869],"iteration":558,"passed_time":0.5392331175,"remaining_time":0.4254057332},
{"learn":[3.778734909],"iteration":559,"passed_time":0.5398851459,"remaining_time":0.4241954718},
{"learn":[3.778652349],"iteration":560,"passed_time":0.5405112605,"remaining_time":0.4229669222},
{"learn":[3.777928006],"iteration":561,"passed_time":0.5411582144,"remaining_time":0.4217567578},
{"learn":[3.776131406],"iteration":562,"passed_time":0.541882248,"remaining_time":0.4206084234},
{"learn":[3.772925617],"iteration":563,"passed_time":0.5425561086,"remaining_time":0.4194228073},
{"learn":[3.7727745],"iteration":564,"passed_time":0.5431810397,"remaining_time":0.4182013315},
{"learn":[3.771763073],"iteration":565,"passed_time":0.5438295481,"remaining_time":0.4170000422},
{"learn":[3.768738162],"iteration":566,"passed_time":0.5445774409,"remaining_time":0.4158765995},
{"learn":[3.767220794],"iteration":567,"passed_time":0.5452648502,"remaining_time":0.4147084776},
{"learn":[3.766691102],"iteration":568,"passed_time":0.545918794,"remaining_time":0.4135166963},
{"learn":[3.766259335],"iteration":569,"passed_time":0.546557715,"remaining_time":0.4123154692},
{"learn":[3.76116362],"iteration":570,"passed_time":0.5472164625,"remaining_time":0.4111311076},
{"learn":[3.758633056],"iteration":571,"passed_time":0.5478766141,"remaining_time":0.4099496343},
{"learn":[3.754603809],"iteration":572,"passed_time":0.5485319318,"remaining_time":0.4087663785},
{"learn":[3.754070549],"iteration":573,"passed_time":0.5492584926,"remaining_time":0.407637836},
{"learn":[3.750534319],"iteration":574,"passed_time":0.5499703014,"remaining_time":0.406499788},
{"learn":[3.746491516],"iteration":575,"passed_time":0.5506757517,"remaining_time":0.4053585395},
{"learn":[3.744210544],"iteration":576,"passed_time":0.5513379892,"remaining_time":0.4041871221},
{"learn":[3.742929991],"iteration":577,"passed_time":0.5520050605,"remaining_time":0.4030209957},
{"learn":[3.740402992],"iteration":578,"passed_time":0.5526750901,"remaining_time":0.4018587443},
{"learn":[3.739644243],"iteration":579,"passed_time":0.553302037,"remaining_time":0.4006669923},
{"learn":[3.737529404],"iteration":580,"passed_time":0.5539502846,"remaining_time":0.3994925461},
{"learn":[3.737196923],"iteration":581,"passed_time":0.5545908704,"remaining_time":0.3983144052},
{"learn":[3.733954464],"iteration":582,"passed_time":0.5552570792,"remaining_time":0.3971564357},
{"learn":[3.731608623],"iteration":583,"passed_time":0.5559074128,"remaining_time":0.395988842},
{"learn":[3.729843952],"iteration":584,"passed_time":0.5565607148,"remaining_time":0.3948251224},
{"learn":[3.727223798],"iteration":585,"passed_time":0.5572104466,"remaining_time":0.3936606227},
{"learn":[3.725351667],"iteration":586,"passed_time":0.5578609607,"remaining_time":0.3924984272},
{"learn":[3.725026912],"iteration":587,"passed_time":0.5584955192,"remaining_time":0.3913267924},
{"learn":[3.721974565],"iteration":588,"passed_time":0.5593674644,"remaining_time":0.390322628},
{"learn":[3.720269493],"iteration":589,"passed_time":0.5601246124,"remaining_time":0.3892391374},
{"learn":[3.718907466],"iteration":590,"passed_time":0.5608573809,"remaining_time":0.3881398795},
{"learn":[3.715602912],"iteration":591,"passed_time":0.5617171204,"remaining_time":0.3871293667},
{"learn":[3.714463059],"iteration":592,"passed_time":0.5624324391,"remaining_time":0.3860202407},
{"learn":[3.710802077],"iteration":593,"passed_time":0.5633573753,"remaining_time":0.3850557145},
{"learn":[3.708032435],"iteration":594,"passed_time":0.5642844577,"remaining_time":0.3840927821},
{"learn":[3.703788939],"iteration":595,"passed_time":0.5649648569,"remaining_time":0.3829627553},
{"learn":[3.702500944],"iteration":596,"passed_time":0.5656226016,"remaining_time":0.3818189421},
{"learn":[3.698196925],"iteration":597,"passed_time":0.566317813,"remaining_time":0.3807019412},
{"learn":[3.69658891],"iteration":598,"passed_time":0.5669848843,"remaining_time":0.3795675102},
{"learn":[3.696124066],"iteration":599,"passed_time":0.5676375144,"remaining_time":0.3784250096},
{"learn":[3.693537052],"iteration":600,"passed_time":0.5682795342,"remaining_time":0.3772770951},
{"learn":[3.691343275],"iteration":601,"passed_time":0.5689350325,"remaining_time":0.3761397723},
{"learn":[3.690973831],"iteration":602,"passed_time":0.5695786369,"remaining_time":0.374996217},
{"learn":[3.686151073],"iteration":603,"passed_time":0.5702644616,"remaining_time":0.373881998},
{"learn":[3.683921982],"iteration":604,"passed_time":0.5709689796,"remaining_time":0.3727813999},
{"learn":[3.679975271],"iteration":605,"passed_time":0.571706632,"remaining_time":0.3717036518},
{"learn":[3.674047638],"iteration":606,"passed_time":0.5724821423,"remaining_time":0.3706515353},
{"learn":[3.673151794],"iteration":607,"passed_time":0.5734258633,"remaining_time":0.3697087803},
{"learn":[3.670953108],"iteration":608,"passed_time":0.5742684134,"remaining_time":0.3687010668},
{"learn":[3.6703947],"iteration":609,"passed_time":0.5750403646,"remaining_time":0.3676487577},
{"learn":[3.668433805],"iteration":610,"passed_time":0.5757625629,"remaining_time":0.3665656906},
{"learn":[3.668304956],"iteration":611,"passed_time":0.5763972218,"remaining_time":0.365428304},
{"learn":[3.667880012],"iteration":612,"passed_time":0.5770589077,"remaining_time":0.3643096204},
{"learn":[3.667282264],"iteration":613,"passed_time":0.5777209747,"remaining_time":0.3631926649},
{"learn":[3.664611483],"iteration":614,"passed_time":0.5783902021,"remaining_time":0.3620816712},
{"learn":[3.662543394],"iteration":615,"passed_time":0.5790613149,"remaining_time":0.3609732872},
{"learn":[3.659041959],"iteration":616,"passed_time":0.5797440107,"remaining_time":0.3598735107},
{"learn":[3.656868545],"iteration":617,"passed_time":0.5804883321,"remaining_time":0.3588131761},
{"learn":[3.654785614],"iteration":618,"passed_time":0.5812186536,"remaining_time":0.3577452456},
{"learn":[3.654566096],"iteration":619,"passed_time":0.5819042176,"remaining_time":0.3566509721},
{"learn":[3.651007045],"iteration":620,"passed_time":0.5826100694,"remaining_time":0.3555703966},
{"learn":[3.648921786],"iteration":621,"passed_time":0.5833003668,"remaining_time":0.3544815734},
{"learn":[3.647655706],"iteration":622,"passed_time":0.5839567476,"remaining_time":0.3533735054},
{"learn":[3.647241144],"iteration":623,"passed_time":0.584669479,"remaining_time":0.3523008399},
{"learn":[3.644195689],"iteration":624,"passed_time":0.5853152094,"remaining_time":0.3511891257},
{"learn":[3.642632246],"iteration":625,"passed_time":0.585958202,"remaining_time":0.3500772645},
{"learn":[3.642523322],"iteration":626,"passed_time":0.5864580868,"remaining_time":0.3488817646},
{"learn":[3.641494659],"iteration":627,"passed_time":0.5871456665,"remaining_time":0.3477996623},
{"learn":[3.63976496],"iteration":628,"passed_time":0.5878876713,"remaining_time":0.3467509158},
{"learn":[3.637945652],"iteration":629,"passed_time":0.5886805211,"remaining_time":0.3457330044},
{"learn":[3.636233667],"iteration":630,"passed_time":0.5894854753,"remaining_time":0.3447228849},
{"learn":[3.635304404],"iteration":631,"passed_time":0.5902133298,"remaining_time":0.3436685212},
{"learn":[3.632234951],"iteration":632,"passed_time":0.5909248578,"remaining_time":0.3426057232},
{"learn":[3.631630987],"iteration":633,"passed_time":0.591608426,"remaining_time":0.3415278926},
{"learn":[3.630301009],"iteration":634,"passed_time":0.592281013,"remaining_time":0.3404449917},
{"learn":[3.629077964],"iteration":635,"passed_time":0.5929336231,"remaining_time":0.3393519478},
{"learn":[3.628004522],"iteration":636,"passed_time":0.5935629868,"remaining_time":0.3382470396},
{"learn":[3.625062876],"iteration":637,"passed_time":0.5941939552,"remaining_time":0.3371445326},
{"learn":[3.624917986],"iteration":638,"passed_time":0.5947964925,"remaining_time":0.3360274394},
{"learn":[3.622887087],"iteration":639,"passed_time":0.5954295468,"remaining_time":0.3349291201},
{"learn":[3.621220865],"iteration":640,"passed_time":0.5960541871,"remaining_time":0.3338275401},
{"learn":[3.621143844],"iteration":641,"passed_time":0.5966463248,"remaining_time":0.3327093213},
{"learn":[3.620822821],"iteration":642,"passed_time":0.5972592618,"remaining_time":0.3316042869},
{"learn":[3.619202826],"iteration":643,"passed_time":0.5978757288,"remaining_time":0.3305027321},
{"learn":[3.618204882],"iteration":644,"passed_time":0.5986387636,"remaining_time":0.3294833505},
{"learn":[3.614259666],"iteration":645,"passed_time":0.5992955455,"remaining_time":0.3284065373},
{"learn":[3.613415661],"iteration":646,"passed_time":0.5999709806,"remaining_time":0.3273411996},
{"learn":[3.611096773],"iteration":647,"passed_time":0.6006089589,"remaining_time":0.3262567184},
{"learn":[3.610820695],"iteration":648,"passed_time":0.6012673555,"remaining_time":0.325184656},
{"learn":[3.609290065],"iteration":649,"passed_time":0.6019157836,"remaining_time":0.3241084988},
{"learn":[3.60897947],"iteration":650,"passed_time":0.6025573221,"remaining_time":0.3230299622},
{"learn":[3.606570702],"iteration":651,"passed_time":0.6031837675,"remaining_time":0.3219447103},
{"learn":[3.606292637],"iteration":652,"passed_time":0.6037921716,"remaining_time":0.3208512765},
{"learn":[3.602753838],"iteration":653,"passed_time":0.6044283548,"remaining_time":0.3197740226},
{"learn":[3.599755869],"iteration":654,"passed_time":0.6050619205,"remaining_time":0.3186967368},
{"learn":[3.599509575],"iteration":655,"passed_time":0.6056669349,"remaining_time":0.3176058317},
{"learn":[3.595337722],"iteration":656,"passed_time":0.606317108,"remaining_time":0.3165399818},
{"learn":[3.595168561],"iteration":657,"passed_time":0.6069165365,"remaining_time":0.3154490205},
{"learn":[3.59290559],"iteration":658,"passed_time":0.6075425708,"remaining_time":0.3143733181},
{"learn":[3.592015928],"iteration":659,"passed_time":0.6081701896,"remaining_time":0.3132997946},
{"learn":[3.590680403],"iteration":660,"passed_time":0.6087763773,"remaining_time":0.3122166292},
{"learn":[3.590361532],"iteration":661,"passed_time":0.6093920721,"remaining_time":0.3111397589},
{"learn":[3.589069739],"iteration":662,"passed_time":0.6100108257,"remaining_time":0.3100658345},
{"learn":[3.585010186],"iteration":663,"passed_time":0.610613373,"remaining_time":0.3089850803},
{"learn":[3.582997552],"iteration":664,"passed_time":0.6112406509,"remaining_time":0.3079182226},
{"learn":[3.582119256],"iteration":665,"passed_time":0.6118770848,"remaining_time":0.3068572768},
{"learn":[3.579019356],"iteration":666,"passed_time":0.612505546,"remaining_time":0.3057936234},
{"learn":[3.57719559],"iteration":667,"passed_time":0.6131361433,"remaining_time":0.3047323347},
{"learn":[3.574050046],"iteration":668,"passed_time":0.613760212,"remaining_time":0.3036691034},
{"learn":[3.572204518],"iteration":669,"passed_time":0.6143919325,"remaining_time":0.3026109518},
{"learn":[3.569508025],"iteration":670,"passed_time":0.615053137,"remaining_time":0.3015685277},
{"learn":[3.566268704],"iteration":671,"passed_time":0.6157138301,"remaining_time":0.3005269885},
{"learn":[3.562564052],"iteration":672,"passed_time":0.6163636422,"remaining_time":0.2994812942},
{"learn":[3.561173586],"iteration":673,"passed_time":0.617057239,"remaining_time":0.2984579524},
{"learn":[3.559551904],"iteration":674,"passed_time":0.6176990182,"remaining_time":0.2974106384},
{"learn":[3.558593054],"iteration":675,"passed_time":0.6183349106,"remaining_time":0.2963617027},
{"learn":[3.555647008],"iteration":676,"passed_time":0.6189903988,"remaining_time":0.2953233365},
{"learn":[3.553100059],"iteration":677,"passed_time":0.6196280261,"remaining_time":0.2942776171},
{"learn":[3.55085578],"iteration":678,"passed_time":0.6203240499,"remaining_time":0.293260707},
{"learn":[3.550737965],"iteration":679,"passed_time":0.6209947415,"remaining_time":0.2922328195},
{"learn":[3.549408772],"iteration":680,"passed_time":0.6216594661,"remaining_time":0.291203186},
{"learn":[3.547390589],"iteration":681,"passed_time":0.6223106621,"remaining_time":0.2901683146},
{"learn":[3.54723575],"iteration":682,"passed_time":0.6229128384,"remaining_time":0.2891118152},
{"learn":[3.543988891],"iteration":683,"passed_time":0.6235409586,"remaining_time":0.28806863},
{"learn":[3.543868508],"iteration":684,"passed_time":0.6241536749,"remaining_time":0.2870195731},
{"learn":[3.542752124],"iteration":685,"passed_time":0.6247570948,"remaining_time":0.2859675332},
{"learn":[3.541334315],"iteration":686,"passed_time":0.62538698,"remaining_time":0.284928857},
{"learn":[3.540208266],"iteration":687,"passed_time":0.626055004,"remaining_time":0.2839086646},
{"learn":[3.537730983],"iteration":688,"passed_time":0.6266941557,"remaining_time":0.2828764621},
{"learn":[3.53419867],"iteration":689,"passed_time":0.6273271197,"remaining_time":0.281842619},
{"learn":[3.532628335],"iteration":690,"passed_time":0.6279599033,"remaining_time":0.2808098554},
{"learn":[3.532204987],"iteration":691,"passed_time":0.6286281077,"remaining_time":0.2797940133},
{"learn":[3.530618147],"iteration":692,"passed_time":0.6293026202,"remaining_time":0.2787819688},
{"learn":[3.528909306],"iteration":693,"passed_time":0.6300606096,"remaining_time":0.277807704},
{"learn":[3.526700678],"iteration":694,"passed_time":0.6307597423,"remaining_time":0.2768082322},
{"learn":[3.526439574],"iteration":695,"passed_time":0.6314102563,"remaining_time":0.2757883878},
{"learn":[3.525784216],"iteration":696,"passed_time":0.6320703477,"remaining_time":0.2747737666},
{"learn":[3.524112693],"iteration":697,"passed_time":0.6327485106,"remaining_time":0.2737679802},
{"learn":[3.522813541],"iteration":698,"passed_time":0.6334116606,"remaining_time":0.2727566665},
{"learn":[3.519148203],"iteration":699,"passed_time":0.6340890814,"remaining_time":0.2717524635},
{"learn":[3.517236747],"iteration":700,"passed_time":0.6347809132,"remaining_time":0.2707553396},
{"learn":[3.515603888],"iteration":701,"passed_time":0.6354688138,"remaining_time":0.2697574167},
{"learn":[3.51263524],"iteration":702,"passed_time":0.6361669436,"remaining_time":0.2687646974},
{"learn":[3.51123442],"iteration":703,"passed_time":0.6368360808,"remaining_time":0.2677606249},
{"learn":[3.50828027],"iteration":704,"passed_time":0.6375053483,"remaining_time":0.2667575571},
{"learn":[3.508265537],"iteration":705,"passed_time":0.6379362765,"remaining_time":0.2656561831},
{"learn":[3.506774876],"iteration":706,"passed_time":0.6386001085,"remaining_time":0.2646532274},
{"learn":[3.50552068],"iteration":707,"passed_time":0.6392472831,"remaining_time":0.2636443597},
{"learn":[3.501973993],"iteration":708,"passed_time":0.6399303599,"remaining_time":0.2626512479},
{"learn":[3.498880354],"iteration":709,"passed_time":0.6406134468,"remaining_time":0.2616590135},
{"learn":[3.497370959],"iteration":710,"passed_time":0.6412611429,"remaining_time":0.2606532634},
{"learn":[3.496050455],"iteration":711,"passed_time":0.6419967306,"remaining_time":0.2596840708},
{"learn":[3.495630067],"iteration":712,"passed_time":0.6429780375,"remaining_time":0.2588144415},
{"learn":[3.49550669],"iteration":713,"passed_time":0.6437762626,"remaining_time":0.257871164},
{"learn":[3.493652375],"iteration":714,"passed_time":0.6445546912,"remaining_time":0.2569204014},
{"learn":[3.491915684],"iteration":715,"passed_time":0.6452682349,"remaining_time":0.2559443837},
{"learn":[3.490303956],"iteration":716,"passed_time":0.6459670166,"remaining_time":0.2549632715},
{"learn":[3.488363853],"iteration":717,"passed_time":0.6466671721,"remaining_time":0.2539834854},
{"learn":[3.485483936],"iteration":718,"passed_time":0.6473743276,"remaining_time":0.2530072129},
{"learn":[3.483763466],"iteration":719,"passed_time":0.6480475564,"remaining_time":0.2520184942},
{"learn":[3.481642352],"iteration":720,"passed_time":0.6487096635,"remaining_time":0.2510263469},
{"learn":[3.479826119],"iteration":721,"passed_time":0.6494127374,"remaining_time":0.2500508878},
{"learn":[3.478588728],"iteration":722,"passed_time":0.6501088314,"remaining_time":0.249073508},
{"learn":[3.475390887],"iteration":723,"passed_time":0.6508127476,"remaining_time":0.2480998872},
{"learn":[3.472636852],"iteration":724,"passed_time":0.6514618376,"remaining_time":0.2471062143},
{"learn":[3.47061883],"iteration":725,"passed_time":0.6521067156,"remaining_time":0.2461119009},
{"learn":[3.46953149],"iteration":726,"passed_time":0.6527299118,"remaining_time":0.2451104071},
{"learn":[3.467217162],"iteration":727,"passed_time":0.6533525866,"remaining_time":0.2441097576},
{"learn":[3.465686216],"iteration":728,"passed_time":0.6539683516,"remaining_time":0.2431075765},
{"learn":[3.462631216],"iteration":729,"passed_time":0.6546084058,"remaining_time":0.2421154378},
{"learn":[3.461451053],"iteration":730,"passed_time":0.6552145434,"remaining_time":0.2411117814},
{"learn":[3.458950469],"iteration":731,"passed_time":0.6558342196,"remaining_time":0.2401141678},
{"learn":[3.458072145],"iteration":732,"passed_time":0.6564528227,"remaining_time":0.2391171946},
{"learn":[3.454364268],"iteration":733,"passed_time":0.6570832696,"remaining_time":0.2381255446},
{"learn":[3.453243406],"iteration":734,"passed_time":0.6577638293,"remaining_time":0.2371529452},
{"learn":[3.453017963],"iteration":735,"passed_time":0.6584036729,"remaining_time":0.2361665349},
{"learn":[3.45201581],"iteration":736,"passed_time":0.6590158277,"remaining_time":0.2351711841},
{"learn":[3.449510107],"iteration":737,"passed_time":0.659629958,"remaining_time":0.2341775732},
{"learn":[3.447189189],"iteration":738,"passed_time":0.6602792686,"remaining_time":0.2331974142},
{"learn":[3.446423605],"iteration":739,"passed_time":0.6608903202,"remaining_time":0.2322047071},
{"learn":[3.445531987],"iteration":740,"passed_time":0.6615199247,"remaining_time":0.2312195148},
{"learn":[3.445328199],"iteration":741,"passed_time":0.6621157429,"remaining_time":0.2302235332},
{"learn":[3.443327544],"iteration":742,"passed_time":0.6627326812,"remaining_time":0.2292359342},
{"learn":[3.441475798],"iteration":743,"passed_time":0.6633482658,"remaining_time":0.2282488656},
{"learn":[3.439046501],"iteration":744,"passed_time":0.6639790335,"remaining_time":0.2272679913},
{"learn":[3.435899469],"iteration":745,"passed_time":0.664607575,"remaining_time":0.2262872976},
{"learn":[3.433988352],"iteration":746,"passed_time":0.6652579587,"remaining_time":0.2253149445},
{"learn":[3.433413263],"iteration":747,"passed_time":0.6658949341,"remaining_time":0.224338935},
{"learn":[3.429944699],"iteration":748,"passed_time":0.6665264842,"remaining_time":0.2233620127},
{"learn":[3.429291634],"iteration":749,"passed_time":0.667145699,"remaining_time":0.2223818997},
{"learn":[3.429175603],"iteration":750,"passed_time":0.6677429613,"remaining_time":0.2213954692},
{"learn":[3.428780323],"iteration":751,"passed_time":0.6683320503,"remaining_time":0.2204073783},
{"learn":[3.423893341],"iteration":752,"passed_time":0.669016471,"remaining_time":0.219451618},
{"learn":[3.421024316],"iteration":753,"passed_time":0.669647319,"remaining_time":0.2184790988},
{"learn":[3.420969872],"iteration":754,"passed_time":0.6702474896,"remaining_time":0.2174975297},
{"learn":[3.419544785],"iteration":755,"passed_time":0.6708783476,"remaining_time":0.2165268741},
{"learn":[3.417057977],"iteration":756,"passed_time":0.6714938118,"remaining_time":0.2155521747},
{"learn":[3.415160245],"iteration":757,"passed_time":0.6721509949,"remaining_time":0.2145917424},
{"learn":[3.412854597],"iteration":758,"passed_time":0.6728311534,"remaining_time":0.2136394044},
{"learn":[3.410926347],"iteration":759,"passed_time":0.6734733638,"remaining_time":0.2126757991},
{"learn":[3.408963843],"iteration":760,"passed_time":0.6741046932,"remaining_time":0.2117096211},
{"learn":[3.407629634],"iteration":761,"passed_time":0.6747270971,"remaining_time":0.2107415343},
{"learn":[3.404384724],"iteration":762,"passed_time":0.6753360126,"remaining_time":0.2097701638},
{"learn":[3.403041656],"iteration":763,"passed_time":0.6759612647,"remaining_time":0.2088047886},
{"learn":[3.401101731],"iteration":764,"passed_time":0.6765969866,"remaining_time":0.2078435188},
{"learn":[3.400890668],"iteration":765,"passed_time":0.6771945498,"remaining_time":0.2068714421},
{"learn":[3.399289941],"iteration":766,"passed_time":0.6778108964,"remaining_time":0.2059060481},
{"learn":[3.399202366],"iteration":767,"passed_time":0.6784051602,"remaining_time":0.2049348921},
{"learn":[3.397447845],"iteration":768,"passed_time":0.6790173249,"remaining_time":0.2039700937},
{"learn":[3.394655341],"iteration":769,"passed_time":0.679640471,"remaining_time":0.2030094913},
{"learn":[3.393228229],"iteration":770,"passed_time":0.680262895,"remaining_time":0.2020495499},
{"learn":[3.389691197],"iteration":771,"passed_time":0.680883223,"remaining_time":0.2010898638},
{"learn":[3.389626772],"iteration":772,"passed_time":0.6814661545,"remaining_time":0.2001200738},
{"learn":[3.388480222],"iteration":773,"passed_time":0.6820825413,"remaining_time":0.1991610521},
{"learn":[3.388215066],"iteration":774,"passed_time":0.6827007332,"remaining_time":0.1982034387},
{"learn":[3.386324358],"iteration":775,"passed_time":0.6833064997,"remaining_time":0.1972431133},
{"learn":[3.383913061],"iteration":776,"passed_time":0.6839322332,"remaining_time":0.1962894311},
{"learn":[3.382839768],"iteration":777,"passed_time":0.6845552188,"remaining_time":0.1953358079},
{"learn":[3.381961844],"iteration":778,"passed_time":0.6852565878,"remaining_time":0.1944052707},
{"learn":[3.381521703],"iteration":779,"passed_time":0.6858816393,"remaining_time":0.1934537957},
{"learn":[3.380918963],"iteration":780,"passed_time":0.6864928313,"remaining_time":0.1924992702},
{"learn":[3.377139006],"iteration":781,"passed_time":0.6871280116,"remaining_time":0.1915523101},
{"learn":[3.376004372],"iteration":782,"passed_time":0.6877433755,"remaining_time":0.1906006545},
{"learn":[3.373826468],"iteration":783,"passed_time":0.6883534042,"remaining_time":0.1896483869},
{"learn":[3.373546786],"iteration":784,"passed_time":0.6889748354,"remaining_time":0.1887001141},
{"learn":[3.372109181],"iteration":785,"passed_time":0.689607649,"remaining_time":0.1877557721},
{"learn":[3.370764924],"iteration":786,"passed_time":0.6902214785,"remaining_time":0.1868070838},
{"learn":[3.367833107],"iteration":787,"passed_time":0.6908489769,"remaining_time":0.1858629227},
{"learn":[3.36450404],"iteration":788,"passed_time":0.6914722133,"remaining_time":0.1849184246},
{"learn":[3.361794558],"iteration":789,"passed_time":0.6921078549,"remaining_time":0.1839780374},
{"learn":[3.356880529],"iteration":790,"passed_time":0.6927620194,"remaining_time":0.1830433149},
{"learn":[3.353843509],"iteration":791,"passed_time":0.6933879434,"remaining_time":0.1821018841},
{"learn":[3.353640253],"iteration":792,"passed_time":0.6939991655,"remaining_time":0.1811574114},
{"learn":[3.353055088],"iteration":793,"passed_time":0.6945903203,"remaining_time":0.1802085718},
{"learn":[3.351415617],"iteration":794,"passed_time":0.6952010009,"remaining_time":0.1792656669},
{"learn":[3.349169061],"iteration":795,"passed_time":0.6958224722,"remaining_time":0.1783263622},
{"learn":[3.346211014],"iteration":796,"passed_time":0.6964576024,"remaining_time":0.1773913341},
{"learn":[3.344560452],"iteration":797,"passed_time":0.697081651,"remaining_time":0.1764542525},
{"learn":[3.344445461],"iteration":798,"passed_time":0.6976823431,"remaining_time":0.1755120788},
{"learn":[3.342608898],"iteration":799,"passed_time":0.6983207225,"remaining_time":0.1745801806},
{"learn":[3.339572899],"iteration":800,"passed_time":0.698938403,"remaining_time":0.1736438729},
{"learn":[3.339309302],"iteration":801,"passed_time":0.6995721393,"remaining_time":0.1727123237},
{"learn":[3.33698088],"iteration":802,"passed_time":0.7002256017,"remaining_time":0.1717863556},
{"learn":[3.334746342],"iteration":803,"passed_time":0.7008638208,"remaining_time":0.1708573493},
{"learn":[3.332048511],"iteration":804,"passed_time":0.701484921,"remaining_time":0.1699249187},
{"learn":[3.331932544],"iteration":805,"passed_time":0.7020918909,"remaining_time":0.1689898596},
{"learn":[3.330541133],"iteration":806,"passed_time":0.7026920314,"remaining_time":0.1680539803},
{"learn":[3.329124989],"iteration":807,"passed_time":0.7033230901,"remaining_time":0.1671262788},
{"learn":[3.32583918],"iteration":808,"passed_time":0.7039423851,"remaining_time":0.1661965335},
{"learn":[3.325287299],"iteration":809,"passed_time":0.7045398881,"remaining_time":0.1652624429},
{"learn":[3.322745162],"iteration":810,"passed_time":0.7051660227,"remaining_time":0.1643358549},
{"learn":[3.319733662],"iteration":811,"passed_time":0.7057880957,"remaining_time":0.1634090665},
{"learn":[3.318080007],"iteration":812,"passed_time":0.7063995785,"remaining_time":0.1624805919},
{"learn":[3.317179538],"iteration":813,"passed_time":0.7070703403,"remaining_time":0.1615664414},
{"learn":[3.315685949],"iteration":814,"passed_time":0.7076816827,"remaining_time":0.1606394004},
{"learn":[3.314944576],"iteration":815,"passed_time":0.708301419,"remaining_time":0.1597150259},
{"learn":[3.312369052],"iteration":816,"passed_time":0.7089745476,"remaining_time":0.1588033564},
{"learn":[3.312321621],"iteration":817,"passed_time":0.7094578651,"remaining_time":0.1578500384},
{"learn":[3.309465776],"iteration":818,"passed_time":0.7101461568,"remaining_time":0.1569431677},
{"learn":[3.308307377],"iteration":819,"passed_time":0.7108396033,"remaining_time":0.1560379617},
{"learn":[3.308076804],"iteration":820,"passed_time":0.7114683753,"remaining_time":0.1551191708},
{"learn":[3.305643326],"iteration":821,"passed_time":0.7121249567,"remaining_time":0.1542071074},
{"learn":[3.304154814],"iteration":822,"passed_time":0.7127428177,"remaining_time":0.1532873375},
{"learn":[3.303076321],"iteration":823,"passed_time":0.7133639079,"remaining_time":0.15236899},
{"learn":[3.301746372],"iteration":824,"passed_time":0.7141954479,"remaining_time":0.1514960041},
{"learn":[3.301345455],"iteration":825,"passed_time":0.7151269829,"remaining_time":0.1506441828},
{"learn":[3.299181039],"iteration":826,"passed_time":0.7161409028,"remaining_time":0.1498094029},
{"learn":[3.297989357],"iteration":827,"passed_time":0.7169936332,"remaining_time":0.1489407064},
{"learn":[3.294775182],"iteration":828,"passed_time":0.7178687674,"remaining_time":0.1480766698},
{"learn":[3.293840636],"iteration":829,"passed_time":0.7186539052,"remaining_time":0.1471941734},
{"learn":[3.289279397],"iteration":830,"passed_time":0.7194546775,"remaining_time":0.1463150909},
{"learn":[3.286204979],"iteration":831,"passed_time":0.7202487106,"remaining_time":0.1454348358},
{"learn":[3.284833593],"iteration":832,"passed_time":0.7210578067,"remaining_time":0.1445578076},
{"learn":[3.283519914],"iteration":833,"passed_time":0.7218948524,"remaining_time":0.1436865054},
{"learn":[3.282853026],"iteration":834,"passed_time":0.7228187365,"remaining_time":0.1428324449},
{"learn":[3.281944673],"iteration":835,"passed_time":0.7236761804,"remaining_time":0.1419651837},
{"learn":[3.279764865],"iteration":836,"passed_time":0.7245333334,"remaining_time":0.1410978893},
{"learn":[3.277468839],"iteration":837,"passed_time":0.7253980169,"remaining_time":0.1402320749},
{"learn":[3.277124974],"iteration":838,"passed_time":0.7261617437,"remaining_time":0.13934689},
{"learn":[3.275636037],"iteration":839,"passed_time":0.7269038588,"remaining_time":0.1384578779},
{"learn":[3.274413635],"iteration":840,"passed_time":0.7277121024,"remaining_time":0.1375817173},
{"learn":[3.272636087],"iteration":841,"passed_time":0.7285337242,"remaining_time":0.1367082285},
{"learn":[3.269644466],"iteration":842,"passed_time":0.7293112603,"remaining_time":0.1358266523},
{"learn":[3.26852083],"iteration":843,"passed_time":0.7300103227,"remaining_time":0.1349308179},
{"learn":[3.267820927],"iteration":844,"passed_time":0.7307258019,"remaining_time":0.1340384607},
{"learn":[3.267331099],"iteration":845,"passed_time":0.7314033731,"remaining_time":0.1331396211},
{"learn":[3.267231014],"iteration":846,"passed_time":0.7320495047,"remaining_time":0.1322356248},
{"learn":[3.267158695],"iteration":847,"passed_time":0.7326729315,"remaining_time":0.131328167},
{"learn":[3.264718705],"iteration":848,"passed_time":0.7333170373,"remaining_time":0.1304250561},
{"learn":[3.261678512],"iteration":849,"passed_time":0.7339559182,"remaining_time":0.1295216326},
{"learn":[3.261368381],"iteration":850,"passed_time":0.734563179,"remaining_time":0.1286132946},
{"learn":[3.260128799],"iteration":851,"passed_time":0.7351743811,"remaining_time":0.1277063479},
{"learn":[3.258972952],"iteration":852,"passed_time":0.7357927936,"remaining_time":0.1268013372},
{"learn":[3.258724846],"iteration":853,"passed_time":0.7364107348,"remaining_time":0.1258969172},
{"learn":[3.25686724],"iteration":854,"passed_time":0.7370402892,"remaining_time":0.1249951368},
{"learn":[3.255750259],"iteration":855,"passed_time":0.737668269,"remaining_time":0.1240937275},
{"learn":[3.254915866],"iteration":856,"passed_time":0.7382752289,"remaining_time":0.1231894489},
{"learn":[3.254348625],"iteration":857,"passed_time":0.7388840642,"remaining_time":0.1222861738},
{"learn":[3.253408514],"iteration":858,"passed_time":0.7395041114,"remaining_time":0.1213854246},
{"learn":[3.253291714],"iteration":859,"passed_time":0.7400894598,"remaining_time":0.1204796795},
{"learn":[3.250186342],"iteration":860,"passed_time":0.7407428721,"remaining_time":0.1195856669},
{"learn":[3.249141318],"iteration":861,"passed_time":0.7413530412,"remaining_time":0.1186852897},
{"learn":[3.246300388],"iteration":862,"passed_time":0.7419926241,"remaining_time":0.1177902543},
{"learn":[3.245205135],"iteration":863,"passed_time":0.7426169736,"remaining_time":0.1168934125},
{"learn":[3.244403535],"iteration":864,"passed_time":0.7432382042,"remaining_time":0.1159967139},
{"learn":[3.244211781],"iteration":865,"passed_time":0.7438320768,"remaining_time":0.1150964183},
{"learn":[3.242286347],"iteration":866,"passed_time":0.7444513619,"remaining_time":0.1142007279},
{"learn":[3.239606746],"iteration":867,"passed_time":0.7450570682,"remaining_time":0.1133036095},
{"learn":[3.236773361],"iteration":868,"passed_time":0.7456697043,"remaining_time":0.1124082063},
{"learn":[3.234552446],"iteration":869,"passed_time":0.7462873246,"remaining_time":0.1115141979},
{"learn":[3.233724647],"iteration":870,"passed_time":0.7469052157,"remaining_time":0.1106208643},
{"learn":[3.230851485],"iteration":871,"passed_time":0.7475205495,"remaining_time":0.1097277871},
{"learn":[3.227728941],"iteration":872,"passed_time":0.7481519391,"remaining_time":0.1088376819},
{"learn":[3.225787575],"iteration":873,"passed_time":0.7487574047,"remaining_time":0.1079444313},
{"learn":[3.222797487],"iteration":874,"passed_time":0.7493875507,"remaining_time":0.1070553644},
{"learn":[3.22137014],"iteration":875,"passed_time":0.7500436808,"remaining_time":0.1061705667},
{"learn":[3.219701963],"iteration":876,"passed_time":0.7506589043,"remaining_time":0.1052805533},
{"learn":[3.21783327],"iteration":877,"passed_time":0.7512815289,"remaining_time":0.1043921942},
{"learn":[3.217713355],"iteration":878,"passed_time":0.7518863928,"remaining_time":0.1035019949},
{"learn":[3.217666091],"iteration":879,"passed_time":0.7524592656,"remaining_time":0.1026080817},
{"learn":[3.214962005],"iteration":880,"passed_time":0.7530773873,"remaining_time":0.1017210092},
{"learn":[3.214081828],"iteration":881,"passed_time":0.7537583695,"remaining_time":0.1008429565},
{"learn":[3.213358337],"iteration":882,"passed_time":0.7544106185,"remaining_time":0.09996154288},
{"learn":[3.210850401],"iteration":883,"passed_time":0.7550562787,"remaining_time":0.09907978318},
{"learn":[3.207810328],"iteration":884,"passed_time":0.7556765265,"remaining_time":0.09819525486},
{"learn":[3.204935073],"iteration":885,"passed_time":0.7564162545,"remaining_time":0.09732669641},
{"learn":[3.20280198],"iteration":886,"passed_time":0.7571187066,"remaining_time":0.09645367965},
{"learn":[3.200663495],"iteration":887,"passed_time":0.7578572115,"remaining_time":0.09558559424},
{"learn":[3.197301669],"iteration":888,"passed_time":0.7586028166,"remaining_time":0.09471868688},
{"learn":[3.195666943],"iteration":889,"passed_time":0.7593764917,"remaining_time":0.09385552144},
{"learn":[3.193886506],"iteration":890,"passed_time":0.7600585657,"remaining_time":0.09298135091},
{"learn":[3.190601248],"iteration":891,"passed_time":0.7607451225,"remaining_time":0.09210815384},
{"learn":[3.188983797],"iteration":892,"passed_time":0.7614056952,"remaining_time":0.09123226135},
{"learn":[3.187365749],"iteration":893,"passed_time":0.7620626075,"remaining_time":0.09035641655},
{"learn":[3.186160771],"iteration":894,"passed_time":0.7627176144,"remaining_time":0.08948083744},
{"learn":[3.185358981],"iteration":895,"passed_time":0.7633665239,"remaining_time":0.08860504295},
{"learn":[3.183832164],"iteration":896,"passed_time":0.7640244691,"remaining_time":0.08773079188},
{"learn":[3.183106966],"iteration":897,"passed_time":0.7646821436,"remaining_time":0.08685699181},
{"learn":[3.182838152],"iteration":898,"passed_time":0.7653123899,"remaining_time":0.08598059108},
{"learn":[3.180835453],"iteration":899,"passed_time":0.7659784182,"remaining_time":0.08510871313},
{"learn":[3.179957348],"iteration":900,"passed_time":0.7666408662,"remaining_time":0.08423689873},
{"learn":[3.179752966],"iteration":901,"passed_time":0.7672917112,"remaining_time":0.08336428792},
{"learn":[3.178851983],"iteration":902,"passed_time":0.7679708469,"remaining_time":0.08249520725},
{"learn":[3.176748586],"iteration":903,"passed_time":0.7686077421,"remaining_time":0.08162206111},
{"learn":[3.172960988],"iteration":904,"passed_time":0.7692784136,"remaining_time":0.08075298265},
{"learn":[3.172794225],"iteration":905,"passed_time":0.7699272228,"remaining_time":0.07988207389},
{"learn":[3.169996507],"iteration":906,"passed_time":0.7707348547,"remaining_time":0.0790279399},
{"learn":[3.16813015],"iteration":907,"passed_time":0.7714508354,"remaining_time":0.07816462209},
{"learn":[3.166920871],"iteration":908,"passed_time":0.772146458,"remaining_time":0.07729959041},
{"learn":[3.16531606],"iteration":909,"passed_time":0.7728256939,"remaining_time":0.07643331039},
{"learn":[3.162035247],"iteration":910,"passed_time":0.773505692,"remaining_time":0.07556751547},
{"learn":[3.16189467],"iteration":911,"passed_time":0.774121798,"remaining_time":0.07469596297},
{"learn":[3.161008416],"iteration":912,"passed_time":0.7747534583,"remaining_time":0.07382645222},
{"learn":[3.160560787],"iteration":913,"passed_time":0.7753734153,"remaining_time":0.07295636074},
{"learn":[3.160416261],"iteration":914,"passed_time":0.7759849483,"remaining_time":0.07208603345},
{"learn":[3.15844291],"iteration":915,"passed_time":0.7766279108,"remaining_time":0.07121915339},
{"learn":[3.155040501],"iteration":916,"passed_time":0.7772541958,"remaining_time":0.07035125219},
{"learn":[3.154937548],"iteration":917,"passed_time":0.7778630612,"remaining_time":0.06948232137},
{"learn":[3.153721161],"iteration":918,"passed_time":0.7784792875,"remaining_time":0.06861460532},
{"learn":[3.153170511],"iteration":919,"passed_time":0.7791073977,"remaining_time":0.06774846937},
{"learn":[3.153113601],"iteration":920,"passed_time":0.7797348059,"remaining_time":0.06688279009},
{"learn":[3.150607379],"iteration":921,"passed_time":0.7804057081,"remaining_time":0.06602130719},
{"learn":[3.148408359],"iteration":922,"passed_time":0.7810761891,"remaining_time":0.06516020212},
{"learn":[3.147495728],"iteration":923,"passed_time":0.7817348163,"remaining_time":0.06429853467},
{"learn":[3.146946235],"iteration":924,"passed_time":0.7823995007,"remaining_time":0.06343779736},
{"learn":[3.14472738],"iteration":925,"passed_time":0.7830553901,"remaining_time":0.06257678064},
{"learn":[3.144469477],"iteration":926,"passed_time":0.7836755075,"remaining_time":0.06171338948},
{"learn":[3.142975516],"iteration":927,"passed_time":0.7843417264,"remaining_time":0.06085409946},
{"learn":[3.14079113],"iteration":928,"passed_time":0.7850111543,"remaining_time":0.05999547035},
{"learn":[3.138173032],"iteration":929,"passed_time":0.7856975607,"remaining_time":0.05913852607},
{"learn":[3.136352813],"iteration":930,"passed_time":0.7863528083,"remaining_time":0.05827963885},
{"learn":[3.133735004],"iteration":931,"passed_time":0.7869968739,"remaining_time":0.05742037278},
{"learn":[3.1319496],"iteration":932,"passed_time":0.7876727804,"remaining_time":0.05656385454},
{"learn":[3.129865343],"iteration":933,"passed_time":0.7883504418,"remaining_time":0.05570784707},
{"learn":[3.129830206],"iteration":934,"passed_time":0.7888510386,"remaining_time":0.05483991177},
{"learn":[3.126676562],"iteration":935,"passed_time":0.7894840628,"remaining_time":0.05398181626},
{"learn":[3.12645665],"iteration":936,"passed_time":0.7901069983,"remaining_time":0.05312352283},
{"learn":[3.126378007],"iteration":937,"passed_time":0.7907131058,"remaining_time":0.05226461893},
{"learn":[3.124621914],"iteration":938,"passed_time":0.791355276,"remaining_time":0.05140859621},
{"learn":[3.123379018],"iteration":939,"passed_time":0.7920624015,"remaining_time":0.05055717456},
{"learn":[3.123332451],"iteration":940,"passed_time":0.7926535563,"remaining_time":0.04969878834},
{"learn":[3.122432444],"iteration":941,"passed_time":0.793297261,"remaining_time":0.04884420503},
{"learn":[3.121889006],"iteration":942,"passed_time":0.7939163354,"remaining_time":0.04798858019},
{"learn":[3.121070914],"iteration":943,"passed_time":0.7945377466,"remaining_time":0.04713359514},
{"learn":[3.118444705],"iteration":944,"passed_time":0.7951665187,"remaining_time":0.04627953283},
{"learn":[3.116820458],"iteration":945,"passed_time":0.7959063172,"remaining_time":0.04543228449},
{"learn":[3.114971041],"iteration":946,"passed_time":0.7965769586,"remaining_time":0.04458139262},
{"learn":[3.114685138],"iteration":947,"passed_time":0.7972222177,"remaining_time":0.04372948874},
{"learn":[3.113399363],"iteration":948,"passed_time":0.7978842546,"remaining_time":0.04287892201},
{"learn":[3.110575399],"iteration":949,"passed_time":0.7985564505,"remaining_time":0.04202928687},
{"learn":[3.110466553],"iteration":950,"passed_time":0.7992780672,"remaining_time":0.04118257129},
{"learn":[3.108691641],"iteration":951,"passed_time":0.7999961338,"remaining_time":0.04033593952},
{"learn":[3.107898017],"iteration":952,"passed_time":0.8007060572,"remaining_time":0.03948917596},
{"learn":[3.105551729],"iteration":953,"passed_time":0.8014264905,"remaining_time":0.03864320604},
{"learn":[3.104824945],"iteration":954,"passed_time":0.8021232564,"remaining_time":0.03779638381},
{"learn":[3.103186704],"iteration":955,"passed_time":0.8028443717,"remaining_time":0.03695099619},
{"learn":[3.102330655],"iteration":956,"passed_time":0.8035284615,"remaining_time":0.03610420464},
{"learn":[3.102291298],"iteration":957,"passed_time":0.8043196565,"remaining_time":0.03526244841},
{"learn":[3.100363529],"iteration":958,"passed_time":0.8050254581,"remaining_time":0.0344171468},
{"learn":[3.097871596],"iteration":959,"passed_time":0.8057289432,"remaining_time":0.0335720393},
{"learn":[3.097372213],"iteration":960,"passed_time":0.8063932666,"remaining_time":0.03272563725},
{"learn":[3.095981813],"iteration":961,"passed_time":0.8070402205,"remaining_time":0.03187892763},
{"learn":[3.095347452],"iteration":962,"passed_time":0.8076720413,"remaining_time":0.03103205143},
{"learn":[3.094728409],"iteration":963,"passed_time":0.8082909152,"remaining_time":0.03018513791},
{"learn":[3.094118537],"iteration":964,"passed_time":0.8089132991,"remaining_time":0.02933882432},
{"learn":[3.093793695],"iteration":965,"passed_time":0.809516047,"remaining_time":0.02849228323},
{"learn":[3.092581602],"iteration":966,"passed_time":0.8101280613,"remaining_time":0.02764656259},
{"learn":[3.091694202],"iteration":967,"passed_time":0.8107533234,"remaining_time":0.02680176276},
{"learn":[3.090298312],"iteration":968,"passed_time":0.8113814136,"remaining_time":0.02595750652},
{"learn":[3.090020107],"iteration":969,"passed_time":0.8119804509,"remaining_time":0.02511279745},
{"learn":[3.088949869],"iteration":970,"passed_time":0.8126080697,"remaining_time":0.02426944801},
{"learn":[3.086700204],"iteration":971,"passed_time":0.8134770063,"remaining_time":0.02343349401},
{"learn":[3.086584317],"iteration":972,"passed_time":0.8141277711,"remaining_time":0.02259141811},
{"learn":[3.084850742],"iteration":973,"passed_time":0.8149335577,"remaining_time":0.0217538732},
{"learn":[3.084239948],"iteration":974,"passed_time":0.8158760041,"remaining_time":0.02091989754},
{"learn":[3.082561673],"iteration":975,"passed_time":0.8166819412,"remaining_time":0.02008234282},
{"learn":[3.07991814],"iteration":976,"passed_time":0.8175431053,"remaining_time":0.01924615294},
{"learn":[3.079350277],"iteration":977,"passed_time":0.8182615029,"remaining_time":0.01840670047},
{"learn":[3.077637462],"iteration":978,"passed_time":0.8189554908,"remaining_time":0.01756697171},
{"learn":[3.076733301],"iteration":979,"passed_time":0.8196682022,"remaining_time":0.01672792249},
{"learn":[3.07594065],"iteration":980,"passed_time":0.820397591,"remaining_time":0.01588945385},
{"learn":[3.072594655],"iteration":981,"passed_time":0.821054754,"remaining_time":0.01504988348},
{"learn":[3.071977674],"iteration":982,"passed_time":0.8217680671,"remaining_time":0.01421165528},
{"learn":[3.069532634],"iteration":983,"passed_time":0.8224068878,"remaining_time":0.01337246972},
{"learn":[3.068870784],"iteration":984,"passed_time":0.8230341757,"remaining_time":0.01253351537},
{"learn":[3.068801463],"iteration":985,"passed_time":0.8236552458,"remaining_time":0.01169490207},
{"learn":[3.067433249],"iteration":986,"passed_time":0.8242860838,"remaining_time":0.01085685825},
{"learn":[3.065611456],"iteration":987,"passed_time":0.8249252054,"remaining_time":0.01001933448},
{"learn":[3.063039162],"iteration":988,"passed_time":0.8255634646,"remaining_time":0.009182202336},
{"learn":[3.06177873],"iteration":989,"passed_time":0.826182178,"remaining_time":0.008345274525},
{"learn":[3.061689148],"iteration":990,"passed_time":0.8267800921,"remaining_time":0.007508598213},
{"learn":[3.058984039],"iteration":991,"passed_time":0.8274113714,"remaining_time":0.00667267235},
{"learn":[3.057492984],"iteration":992,"passed_time":0.8280965743,"remaining_time":0.005837538792},
{"learn":[3.057290731],"iteration":993,"passed_time":0.8287536972,"remaining_time":0.005002537408},
{"learn":[3.056068348],"iteration":994,"passed_time":0.8294243687,"remaining_time":0.004167961652},
{"learn":[3.054987307],"iteration":995,"passed_time":0.8300937666,"remaining_time":0.003333709906},
{"learn":[3.054200234],"iteration":996,"passed_time":0.8307585012,"remaining_time":0.002499774828},
{"learn":[3.052732869],"iteration":997,"passed_time":0.8314137989,"remaining_time":0.001666159918},
{"learn":[3.051787862],"iteration":998,"passed_time":0.8320667399,"remaining_time":0.0008328996395},
{"learn":[3.051366222],"iteration":999,"passed_time":0.8327537981,"remaining_time":0}
]}